package io.undertow.client.http;

import io.undertow.util.BadRequestException;
import io.undertow.util.HttpString;
import java.nio.ByteBuffer;
import java.util.Map;

public class HttpResponseParser$$generated extends HttpResponseParser {
  private static final byte[] STATE_BYTES_407;
  
  private static final byte[] STATE_BYTES_405;
  
  private static final HttpString HTTP_STRING_318;
  
  private static final byte[] STATE_BYTES_409;
  
  private static final HttpString HTTP_STRING_439;
  
  private static final HttpString HTTP_STRING_205;
  
  private static final HttpString HTTP_STRING_326;
  
  private static final HttpString HTTP_STRING_447;
  
  private static final HttpString HTTP_STRING_204;
  
  private static final HttpString HTTP_STRING_324;
  
  private static final HttpString HTTP_STRING_445;
  
  private static final HttpString HTTP_STRING_202;
  
  private static final byte[] STATE_BYTES_403;
  
  private static final HttpString HTTP_STRING_322;
  
  private static final HttpString HTTP_STRING_443;
  
  private static final HttpString HTTP_STRING_200;
  
  private static final byte[] STATE_BYTES_401;
  
  private static final HttpString HTTP_STRING_320;
  
  private static final HttpString HTTP_STRING_441;
  
  private static final byte[] STATE_BYTES_418;
  
  private static final byte[] STATE_BYTES_416;
  
  private static final HttpString HTTP_STRING_308;
  
  private static final HttpString HTTP_STRING_429;
  
  private static final HttpString HTTP_STRING_306;
  
  private static final HttpString HTTP_STRING_427;
  
  private static final HttpString HTTP_STRING_316;
  
  private static final HttpString HTTP_STRING_437;
  
  private static final HttpString HTTP_STRING_314;
  
  private static final HttpString HTTP_STRING_435;
  
  private static final HttpString HTTP_STRING_312;
  
  private static final byte[] STATE_BYTES_414;
  
  private static final HttpString HTTP_STRING_433;
  
  private static final HttpString HTTP_STRING_310;
  
  private static final HttpString HTTP_STRING_431;
  
  private static final HttpString HTTP_STRING_419;
  
  private static final HttpString HTTP_STRING_417;
  
  private static final HttpString HTTP_STRING_305;
  
  private static final HttpString HTTP_STRING_304;
  
  private static final HttpString HTTP_STRING_425;
  
  private static final HttpString HTTP_STRING_302;
  
  private static final HttpString HTTP_STRING_423;
  
  private static final byte[] STATE_BYTES_502;
  
  private static final HttpString HTTP_STRING_300;
  
  private static final HttpString HTTP_STRING_421;
  
  private static final byte[] STATE_BYTES_500;
  
  private static final HttpString HTTP_STRING_408;
  
  private static final HttpString HTTP_STRING_406;
  
  private static final HttpString HTTP_STRING_415;
  
  private static final HttpString HTTP_STRING_413;
  
  private static final HttpString HTTP_STRING_412;
  
  private static final HttpString HTTP_STRING_411;
  
  private static final HttpString HTTP_STRING_410;
  
  private static final byte[] STATE_BYTES_208;
  
  private static final byte[] STATE_BYTES_329;
  
  private static final byte[] STATE_BYTES_206;
  
  private static final byte[] STATE_BYTES_327;
  
  private static final byte[] STATE_BYTES_448;
  
  private static final byte[] STATE_BYTES_201;
  
  private static final HttpString HTTP_STRING_404;
  
  private static final byte[] STATE_BYTES_321;
  
  private static final byte[] STATE_BYTES_442;
  
  private static final HttpString HTTP_STRING_402;
  
  private static final byte[] STATE_BYTES_440;
  
  private static final HttpString HTTP_STRING_400;
  
  private static final byte[] STATE_BYTES_325;
  
  private static final byte[] STATE_BYTES_446;
  
  private static final byte[] STATE_BYTES_203;
  
  private static final byte[] STATE_BYTES_323;
  
  private static final byte[] STATE_BYTES_444;
  
  private static final byte[] STATE_BYTES_218;
  
  private static final byte[] STATE_BYTES_339;
  
  private static final byte[] STATE_BYTES_459;
  
  private static final byte[] STATE_BYTES_212;
  
  private static final byte[] STATE_BYTES_333;
  
  private static final byte[] STATE_BYTES_453;
  
  private static final byte[] STATE_BYTES_210;
  
  private static final byte[] STATE_BYTES_331;
  
  private static final byte[] STATE_BYTES_451;
  
  private static final byte[] STATE_BYTES_216;
  
  private static final byte[] STATE_BYTES_337;
  
  private static final byte[] STATE_BYTES_457;
  
  private static final byte[] STATE_BYTES_214;
  
  private static final byte[] STATE_BYTES_455;
  
  private static final byte[] STATE_BYTES_307;
  
  private static final byte[] STATE_BYTES_428;
  
  private static final byte[] STATE_BYTES_426;
  
  private static final byte[] STATE_BYTES_309;
  
  private static final HttpString HTTP_STRING_503;
  
  private static final byte[] STATE_BYTES_420;
  
  private static final HttpString HTTP_STRING_501;
  
  private static final byte[] STATE_BYTES_303;
  
  private static final byte[] STATE_BYTES_424;
  
  private static final byte[] STATE_BYTES_301;
  
  private static final byte[] STATE_BYTES_422;
  
  private static final byte[] STATE_BYTES_319;
  
  private static final byte[] STATE_BYTES_317;
  
  private static final byte[] STATE_BYTES_438;
  
  private static final byte[] STATE_BYTES_311;
  
  private static final byte[] STATE_BYTES_432;
  
  private static final byte[] STATE_BYTES_430;
  
  private static final byte[] STATE_BYTES_315;
  
  private static final byte[] STATE_BYTES_436;
  
  private static final byte[] STATE_BYTES_313;
  
  private static final byte[] STATE_BYTES_434;
  
  private static final HttpString HTTP_STRING_286;
  
  private static final HttpString HTTP_STRING_164;
  
  private static final HttpString HTTP_STRING_284;
  
  private static final HttpString HTTP_STRING_162;
  
  private static final byte[] STATE_BYTES_120;
  
  private static final byte[] STATE_BYTES_241;
  
  private static final HttpString HTTP_STRING_282;
  
  private static final HttpString HTTP_STRING_160;
  
  private static final byte[] STATE_BYTES_361;
  
  private static final byte[] STATE_BYTES_482;
  
  private static final byte[] STATE_BYTES_71;
  
  private static final HttpString HTTP_STRING_280;
  
  private static final byte[] STATE_BYTES_480;
  
  private static final byte[] STATE_BYTES_73;
  
  private static final byte[] STATE_BYTES_124;
  
  private static final byte[] STATE_BYTES_245;
  
  private static final byte[] STATE_BYTES_365;
  
  private static final byte[] STATE_BYTES_486;
  
  private static final byte[] STATE_BYTES_122;
  
  private static final byte[] STATE_BYTES_243;
  
  private static final byte[] STATE_BYTES_363;
  
  private static final byte[] STATE_BYTES_484;
  
  private static final byte[] STATE_BYTES_77;
  
  private static final byte[] STATE_BYTES_128;
  
  private static final byte[] STATE_BYTES_249;
  
  private static final HttpString HTTP_STRING_168;
  
  private static final byte[] STATE_BYTES_369;
  
  private static final byte[] STATE_BYTES_79;
  
  private static final byte[] STATE_BYTES_126;
  
  private static final byte[] STATE_BYTES_247;
  
  private static final HttpString HTTP_STRING_288;
  
  private static final HttpString HTTP_STRING_166;
  
  private static final byte[] STATE_BYTES_367;
  
  private static final byte[] STATE_BYTES_488;
  
  private static final byte[] STATE_BYTES_59;
  
  private static final HttpString HTTP_STRING_154;
  
  private static final HttpString HTTP_STRING_396;
  
  private static final byte[] STATE_BYTES_490;
  
  private static final HttpString HTTP_STRING_274;
  
  private static final HttpString HTTP_STRING_152;
  
  private static final HttpString HTTP_STRING_394;
  
  private static final HttpString HTTP_STRING_272;
  
  private static final HttpString HTTP_STRING_150;
  
  private static final byte[] STATE_BYTES_373;
  
  private static final HttpString HTTP_STRING_392;
  
  private static final byte[] STATE_BYTES_494;
  
  private static final byte[] STATE_BYTES_130;
  
  private static final byte[] STATE_BYTES_251;
  
  private static final HttpString HTTP_STRING_270;
  
  private static final byte[] STATE_BYTES_371;
  
  private static final HttpString HTTP_STRING_390;
  
  private static final byte[] STATE_BYTES_492;
  
  private static final byte[] STATE_BYTES_61;
  
  private static final byte[] STATE_BYTES_135;
  
  private static final byte[] STATE_BYTES_377;
  
  private static final byte[] STATE_BYTES_498;
  
  private static final byte[] STATE_BYTES_63;
  
  private static final byte[] STATE_BYTES_255;
  
  private static final byte[] STATE_BYTES_375;
  
  private static final byte[] STATE_BYTES_496;
  
  private static final byte[] STATE_BYTES_65;
  
  private static final byte[] STATE_BYTES_132;
  
  private static final byte[] STATE_BYTES_253;
  
  private static final byte[] STATE_BYTES_139;
  
  private static final HttpString HTTP_STRING_158;
  
  private static final byte[] STATE_BYTES_67;
  
  private static final byte[] STATE_BYTES_259;
  
  private static final HttpString HTTP_STRING_278;
  
  private static final byte[] STATE_BYTES_137;
  
  private static final HttpString HTTP_STRING_156;
  
  private static final byte[] STATE_BYTES_379;
  
  private static final HttpString HTTP_STRING_398;
  
  private static final byte[] STATE_BYTES_69;
  
  private static final byte[] STATE_BYTES_257;
  
  private static final HttpString HTTP_STRING_276;
  
  private static final byte[] STATE_BYTES_108;
  
  private static final byte[] STATE_BYTES_229;
  
  private static final byte[] STATE_BYTES_349;
  
  private static final HttpString HTTP_STRING_264;
  
  private static final HttpString HTTP_STRING_142;
  
  private static final HttpString HTTP_STRING_263;
  
  private static final HttpString HTTP_STRING_384;
  
  private static final HttpString HTTP_STRING_262;
  
  private static final HttpString HTTP_STRING_140;
  
  private static final HttpString HTTP_STRING_382;
  
  private static final HttpString HTTP_STRING_260;
  
  private static final HttpString HTTP_STRING_380;
  
  private static final byte[] STATE_BYTES_102;
  
  private static final byte[] STATE_BYTES_96;
  
  private static final byte[] STATE_BYTES_222;
  
  private static final byte[] STATE_BYTES_343;
  
  private static final byte[] STATE_BYTES_464;
  
  private static final byte[] STATE_BYTES_100;
  
  private static final byte[] STATE_BYTES_98;
  
  private static final HttpString HTTP_STRING_148;
  
  private static final byte[] STATE_BYTES_220;
  
  private static final byte[] STATE_BYTES_341;
  
  private static final byte[] STATE_BYTES_462;
  
  private static final byte[] STATE_BYTES_106;
  
  private static final byte[] STATE_BYTES_227;
  
  private static final HttpString HTTP_STRING_268;
  
  private static final HttpString HTTP_STRING_146;
  
  private static final byte[] STATE_BYTES_347;
  
  private static final HttpString HTTP_STRING_388;
  
  private static final byte[] STATE_BYTES_468;
  
  private static final byte[] STATE_BYTES_104;
  
  private static final byte[] STATE_BYTES_225;
  
  private static final HttpString HTTP_STRING_266;
  
  private static final HttpString HTTP_STRING_144;
  
  private static final byte[] STATE_BYTES_345;
  
  private static final HttpString HTTP_STRING_386;
  
  private static final byte[] STATE_BYTES_466;
  
  private static final byte[] STATE_BYTES_118;
  
  private static final byte[] STATE_BYTES_239;
  
  private static final HttpString HTTP_STRING_374;
  
  private static final HttpString HTTP_STRING_495;
  
  private static final HttpString HTTP_STRING_131;
  
  private static final HttpString HTTP_STRING_252;
  
  private static final HttpString HTTP_STRING_372;
  
  private static final HttpString HTTP_STRING_493;
  
  private static final HttpString HTTP_STRING_250;
  
  private static final byte[] STATE_BYTES_351;
  
  private static final HttpString HTTP_STRING_370;
  
  private static final byte[] STATE_BYTES_472;
  
  private static final HttpString HTTP_STRING_491;
  
  private static final byte[] STATE_BYTES_81;
  
  private static final byte[] STATE_BYTES_470;
  
  private static final byte[] STATE_BYTES_83;
  
  private static final byte[] STATE_BYTES_355;
  
  private static final byte[] STATE_BYTES_476;
  
  private static final byte[] STATE_BYTES_85;
  
  private static final byte[] STATE_BYTES_112;
  
  private static final byte[] STATE_BYTES_233;
  
  private static final HttpString HTTP_STRING_138;
  
  private static final byte[] STATE_BYTES_353;
  
  private static final byte[] STATE_BYTES_474;
  
  private static final byte[] STATE_BYTES_87;
  
  private static final byte[] STATE_BYTES_110;
  
  private static final byte[] STATE_BYTES_231;
  
  private static final HttpString HTTP_STRING_258;
  
  private static final HttpString HTTP_STRING_136;
  
  private static final byte[] STATE_BYTES_359;
  
  private static final HttpString HTTP_STRING_378;
  
  private static final HttpString HTTP_STRING_499;
  
  private static final byte[] STATE_BYTES_89;
  
  private static final byte[] STATE_BYTES_116;
  
  private static final byte[] STATE_BYTES_237;
  
  private static final HttpString HTTP_STRING_256;
  
  private static final HttpString HTTP_STRING_134;
  
  private static final byte[] STATE_BYTES_357;
  
  private static final HttpString HTTP_STRING_376;
  
  private static final byte[] STATE_BYTES_478;
  
  private static final HttpString HTTP_STRING_497;
  
  private static final byte[] STATE_BYTES_114;
  
  private static final HttpString HTTP_STRING_133;
  
  private static final byte[] STATE_BYTES_235;
  
  private static final HttpString HTTP_STRING_254;
  
  private static final byte[] STATE_BYTES_26;
  
  private static final byte[] STATE_BYTES_28;
  
  private static final HttpString HTTP_STRING_119;
  
  private static final HttpString HTTP_STRING_121;
  
  private static final HttpString HTTP_STRING_242;
  
  private static final byte[] STATE_BYTES_281;
  
  private static final HttpString HTTP_STRING_362;
  
  private static final HttpString HTTP_STRING_483;
  
  private static final HttpString HTTP_STRING_240;
  
  private static final HttpString HTTP_STRING_360;
  
  private static final HttpString HTTP_STRING_481;
  
  private static final byte[] STATE_BYTES_285;
  
  private static final byte[] STATE_BYTES_163;
  
  private static final byte[] STATE_BYTES_283;
  
  private static final byte[] STATE_BYTES_161;
  
  private static final HttpString HTTP_STRING_129;
  
  private static final byte[] STATE_BYTES_289;
  
  private static final byte[] STATE_BYTES_30;
  
  private static final byte[] STATE_BYTES_167;
  
  private static final HttpString HTTP_STRING_127;
  
  private static final HttpString HTTP_STRING_248;
  
  private static final byte[] STATE_BYTES_287;
  
  private static final byte[] STATE_BYTES_32;
  
  private static final byte[] STATE_BYTES_165;
  
  private static final HttpString HTTP_STRING_368;
  
  private static final HttpString HTTP_STRING_489;
  
  private static final HttpString HTTP_STRING_125;
  
  private static final HttpString HTTP_STRING_246;
  
  private static final byte[] STATE_BYTES_34;
  
  private static final HttpString HTTP_STRING_366;
  
  private static final HttpString HTTP_STRING_487;
  
  private static final HttpString HTTP_STRING_123;
  
  private static final HttpString HTTP_STRING_244;
  
  private static final byte[] STATE_BYTES_36;
  
  private static final byte[] STATE_BYTES_169;
  
  private static final HttpString HTTP_STRING_364;
  
  private static final HttpString HTTP_STRING_485;
  
  private static final byte[] STATE_BYTES_16;
  
  private static final byte[] STATE_BYTES_18;
  
  private static final HttpString HTTP_STRING_109;
  
  private static final byte[] STATE_BYTES_171;
  
  private static final HttpString HTTP_STRING_352;
  
  private static final HttpString HTTP_STRING_473;
  
  private static final HttpString HTTP_STRING_230;
  
  private static final byte[] STATE_BYTES_291;
  
  private static final HttpString HTTP_STRING_350;
  
  private static final HttpString HTTP_STRING_471;
  
  private static final byte[] STATE_BYTES_175;
  
  private static final byte[] STATE_BYTES_295;
  
  private static final byte[] STATE_BYTES_173;
  
  private static final byte[] STATE_BYTES_293;
  
  private static final byte[] STATE_BYTES_179;
  
  private static final HttpString HTTP_STRING_117;
  
  private static final HttpString HTTP_STRING_238;
  
  private static final byte[] STATE_BYTES_299;
  
  private static final byte[] STATE_BYTES_177;
  
  private static final HttpString HTTP_STRING_358;
  
  private static final HttpString HTTP_STRING_479;
  
  private static final HttpString HTTP_STRING_115;
  
  private static final HttpString HTTP_STRING_236;
  
  private static final byte[] STATE_BYTES_297;
  
  private static final byte[] STATE_BYTES_22;
  
  private static final HttpString HTTP_STRING_356;
  
  private static final HttpString HTTP_STRING_477;
  
  private static final HttpString HTTP_STRING_113;
  
  private static final HttpString HTTP_STRING_234;
  
  private static final byte[] STATE_BYTES_24;
  
  private static final HttpString HTTP_STRING_354;
  
  private static final HttpString HTTP_STRING_475;
  
  private static final HttpString HTTP_STRING_111;
  
  private static final HttpString HTTP_STRING_232;
  
  private static final byte[] STATE_BYTES_48;
  
  private static final HttpString HTTP_STRING_219;
  
  private static final HttpString HTTP_STRING_340;
  
  private static final HttpString HTTP_STRING_461;
  
  private static final HttpString HTTP_STRING_460;
  
  private static final byte[] STATE_BYTES_141;
  
  private static final byte[] STATE_BYTES_383;
  
  private static final byte[] STATE_BYTES_261;
  
  private static final byte[] STATE_BYTES_381;
  
  private static final byte[] STATE_BYTES_51;
  
  private static final HttpString HTTP_STRING_107;
  
  private static final HttpString HTTP_STRING_228;
  
  private static final byte[] STATE_BYTES_267;
  
  private static final byte[] STATE_BYTES_145;
  
  private static final HttpString HTTP_STRING_348;
  
  private static final byte[] STATE_BYTES_387;
  
  private static final HttpString HTTP_STRING_469;
  
  private static final byte[] STATE_BYTES_53;
  
  private static final HttpString HTTP_STRING_105;
  
  private static final HttpString HTTP_STRING_226;
  
  private static final byte[] STATE_BYTES_265;
  
  private static final byte[] STATE_BYTES_143;
  
  private static final HttpString HTTP_STRING_346;
  
  private static final byte[] STATE_BYTES_385;
  
  private static final HttpString HTTP_STRING_467;
  
  private static final byte[] STATE_BYTES_55;
  
  private static final HttpString HTTP_STRING_103;
  
  private static final HttpString HTTP_STRING_224;
  
  private static final byte[] STATE_BYTES_149;
  
  private static final HttpString HTTP_STRING_223;
  
  private static final HttpString HTTP_STRING_344;
  
  private static final HttpString HTTP_STRING_465;
  
  private static final byte[] STATE_BYTES_57;
  
  private static final HttpString HTTP_STRING_101;
  
  private static final byte[] STATE_BYTES_269;
  
  private static final byte[] STATE_BYTES_147;
  
  private static final HttpString HTTP_STRING_221;
  
  private static final HttpString HTTP_STRING_342;
  
  private static final byte[] STATE_BYTES_389;
  
  private static final HttpString HTTP_STRING_463;
  
  private static final byte[] STATE_BYTES_38;
  
  private static final HttpString HTTP_STRING_209;
  
  private static final HttpString HTTP_STRING_207;
  
  private static final HttpString HTTP_STRING_328;
  
  private static final HttpString HTTP_STRING_449;
  
  private static final HttpString HTTP_STRING_330;
  
  private static final byte[] STATE_BYTES_391;
  
  private static final HttpString HTTP_STRING_450;
  
  private static final byte[] STATE_BYTES_153;
  
  private static final byte[] STATE_BYTES_395;
  
  private static final byte[] STATE_BYTES_273;
  
  private static final byte[] STATE_BYTES_151;
  
  private static final byte[] STATE_BYTES_393;
  
  private static final byte[] STATE_BYTES_271;
  
  private static final byte[] STATE_BYTES_40;
  
  private static final byte[] STATE_BYTES_157;
  
  private static final HttpString HTTP_STRING_217;
  
  private static final HttpString HTTP_STRING_338;
  
  private static final byte[] STATE_BYTES_399;
  
  private static final byte[] STATE_BYTES_277;
  
  private static final HttpString HTTP_STRING_458;
  
  private static final byte[] STATE_BYTES_42;
  
  private static final byte[] STATE_BYTES_155;
  
  private static final HttpString HTTP_STRING_215;
  
  private static final HttpString HTTP_STRING_336;
  
  private static final byte[] STATE_BYTES_397;
  
  private static final byte[] STATE_BYTES_275;
  
  private static final HttpString HTTP_STRING_335;
  
  private static final HttpString HTTP_STRING_456;
  
  private static final byte[] STATE_BYTES_44;
  
  private static final HttpString HTTP_STRING_213;
  
  private static final HttpString HTTP_STRING_334;
  
  private static final HttpString HTTP_STRING_454;
  
  private static final byte[] STATE_BYTES_46;
  
  private static final byte[] STATE_BYTES_159;
  
  private static final HttpString HTTP_STRING_211;
  
  private static final HttpString HTTP_STRING_332;
  
  private static final byte[] STATE_BYTES_279;
  
  private static final HttpString HTTP_STRING_452;
  
  private static final HttpString HTTP_STRING_60;
  
  private static final HttpString HTTP_STRING_66;
  
  private static final HttpString HTTP_STRING_68;
  
  private static final HttpString HTTP_STRING_62;
  
  private static final HttpString HTTP_STRING_64;
  
  private static final HttpString HTTP_STRING_70;
  
  private static final HttpString HTTP_STRING_76;
  
  private static final HttpString HTTP_STRING_78;
  
  private static final HttpString HTTP_STRING_72;
  
  private static final HttpString HTTP_STRING_74;
  
  private static final HttpString HTTP_STRING_75;
  
  private static final HttpString HTTP_STRING_9;
  
  private static final HttpString HTTP_STRING_5;
  
  private static final HttpString HTTP_STRING_6;
  
  private static final HttpString HTTP_STRING_7;
  
  private static final HttpString HTTP_STRING_3;
  
  private static final HttpString HTTP_STRING_4;
  
  private static final HttpString HTTP_STRING_80;
  
  private static final HttpString HTTP_STRING_82;
  
  private static final HttpString HTTP_STRING_88;
  
  private static final byte[] STATE_BYTES_181;
  
  private static final HttpString HTTP_STRING_84;
  
  private static final byte[] STATE_BYTES_185;
  
  private static final HttpString HTTP_STRING_86;
  
  private static final byte[] STATE_BYTES_183;
  
  private static final byte[] STATE_BYTES_189;
  
  private static final byte[] STATE_BYTES_10;
  
  private static final byte[] STATE_BYTES_187;
  
  private static final byte[] STATE_BYTES_12;
  
  private static final HttpString HTTP_STRING_90;
  
  private static final HttpString HTTP_STRING_91;
  
  private static final HttpString HTTP_STRING_92;
  
  private static final HttpString HTTP_STRING_93;
  
  private static final byte[] STATE_BYTES_193;
  
  private static final HttpString HTTP_STRING_99;
  
  private static final byte[] STATE_BYTES_191;
  
  private static final HttpString HTTP_STRING_94;
  
  private static final byte[] STATE_BYTES_197;
  
  private static final HttpString HTTP_STRING_95;
  
  private static final byte[] STATE_BYTES_195;
  
  private static final HttpString HTTP_STRING_97;
  
  private static final byte[] STATE_BYTES_199;
  
  private static final HttpString HTTP_STRING_190;
  
  private static final HttpString HTTP_STRING_198;
  
  private static final HttpString HTTP_STRING_196;
  
  private static final HttpString HTTP_STRING_194;
  
  private static final HttpString HTTP_STRING_192;
  
  private static final HttpString HTTP_STRING_186;
  
  private static final HttpString HTTP_STRING_184;
  
  private static final HttpString HTTP_STRING_182;
  
  private static final HttpString HTTP_STRING_180;
  
  private static final HttpString HTTP_STRING_188;
  
  private static final HttpString HTTP_STRING_176;
  
  private static final HttpString HTTP_STRING_296;
  
  private static final HttpString HTTP_STRING_174;
  
  private static final HttpString HTTP_STRING_294;
  
  private static final HttpString HTTP_STRING_172;
  
  private static final HttpString HTTP_STRING_292;
  
  private static final HttpString HTTP_STRING_170;
  
  private static final HttpString HTTP_STRING_290;
  
  private static final HttpString HTTP_STRING_178;
  
  private static final HttpString HTTP_STRING_298;
  
  private static final byte[] STATE_BYTES_8 = "HTTP/0.9".getBytes("ISO-8859-1");
  
  private static final HttpString HTTP_STRING_11;
  
  private static final HttpString HTTP_STRING_13;
  
  private static final HttpString HTTP_STRING_19;
  
  private static final HttpString HTTP_STRING_14;
  
  private static final HttpString HTTP_STRING_15;
  
  private static final HttpString HTTP_STRING_17;
  
  private static final HttpString HTTP_STRING_21;
  
  private static final HttpString HTTP_STRING_23;
  
  private static final HttpString HTTP_STRING_29;
  
  private static final HttpString HTTP_STRING_25;
  
  private static final HttpString HTTP_STRING_27;
  
  private static final HttpString HTTP_STRING_33;
  
  private static final HttpString HTTP_STRING_35;
  
  private static final HttpString HTTP_STRING_31;
  
  private static final HttpString HTTP_STRING_37;
  
  private static final HttpString HTTP_STRING_39;
  
  private static final HttpString HTTP_STRING_43;
  
  private static final HttpString HTTP_STRING_45;
  
  private static final HttpString HTTP_STRING_41;
  
  private static final HttpString HTTP_STRING_47;
  
  private static final HttpString HTTP_STRING_49;
  
  private static final HttpString HTTP_STRING_54;
  
  private static final HttpString HTTP_STRING_56;
  
  private static final HttpString HTTP_STRING_50;
  
  private static final HttpString HTTP_STRING_52;
  
  private static final HttpString HTTP_STRING_58;
  
  protected final void handleHeader(ByteBuffer paramByteBuffer, ResponseParseState paramResponseParseState, HttpResponseBuilder paramHttpResponseBuilder) throws BadRequestException {
    // Byte code:
    //   0: aload_1
    //   1: invokevirtual hasRemaining : ()Z
    //   4: ifne -> 9
    //   7: iconst_0
    //   8: return
    //   9: aload_2
    //   10: dup
    //   11: getfield stringBuilder : Ljava/lang/StringBuilder;
    //   14: astore #7
    //   16: dup
    //   17: getfield parseState : I
    //   20: dup
    //   21: istore #4
    //   23: ifeq -> 470
    //   26: dup
    //   27: getfield pos : I
    //   30: istore #5
    //   32: dup
    //   33: getfield current : Lio/undertow/util/HttpString;
    //   36: astore #6
    //   38: getfield currentBytes : [B
    //   41: astore #8
    //   43: iload #4
    //   45: tableswitch default -> 164, -2 -> 228, -1 -> 386, 0 -> 480, 1 -> 736, 2 -> 860, 3 -> 971, 4 -> 1055, 5 -> 1166, 6 -> 1251, 7 -> 1336, 8 -> 1421, 9 -> 1506, 10 -> 1731, 11 -> 1886, 12 -> 2011, 13 -> 2136, 14 -> 2221, 15 -> 2346, 16 -> 2431, 17 -> 2556, 18 -> 2668, 19 -> 2793, 20 -> 2878, 21 -> 2963, 22 -> 3088, 23 -> 3213
    //   164: new java/lang/RuntimeException
    //   167: dup
    //   168: ldc 'Invalid character'
    //   170: invokespecial <init> : (Ljava/lang/String;)V
    //   173: athrow
    //   174: aload_2
    //   175: dup
    //   176: dup
    //   177: dup
    //   178: dup
    //   179: iload #5
    //   181: putfield pos : I
    //   184: aload #6
    //   186: putfield current : Lio/undertow/util/HttpString;
    //   189: aload #8
    //   191: putfield currentBytes : [B
    //   194: iload #4
    //   196: putfield parseState : I
    //   199: return
    //   200: aload_2
    //   201: dup
    //   202: dup
    //   203: dup
    //   204: dup
    //   205: iconst_0
    //   206: putfield pos : I
    //   209: aconst_null
    //   210: putfield current : Lio/undertow/util/HttpString;
    //   213: aconst_null
    //   214: putfield currentBytes : [B
    //   217: aload #7
    //   219: iconst_0
    //   220: invokevirtual setLength : (I)V
    //   223: iconst_0
    //   224: putfield parseState : I
    //   227: return
    //   228: aload_1
    //   229: invokevirtual hasRemaining : ()Z
    //   232: ifeq -> 174
    //   235: aload_1
    //   236: invokevirtual get : ()B
    //   239: dup
    //   240: dup
    //   241: bipush #58
    //   243: if_icmpeq -> 331
    //   246: dup
    //   247: bipush #32
    //   249: if_icmpeq -> 323
    //   252: dup
    //   253: bipush #13
    //   255: if_icmpeq -> 331
    //   258: dup
    //   259: bipush #10
    //   261: if_icmpeq -> 331
    //   264: aload #8
    //   266: arraylength
    //   267: iload #5
    //   269: if_icmpeq -> 296
    //   272: dup
    //   273: aload #8
    //   275: iload #5
    //   277: baload
    //   278: isub
    //   279: ifne -> 296
    //   282: pop2
    //   283: iinc #5, 1
    //   286: aload_1
    //   287: invokevirtual hasRemaining : ()Z
    //   290: ifeq -> 174
    //   293: goto -> 228
    //   296: iconst_m1
    //   297: istore #4
    //   299: aload #7
    //   301: aload #6
    //   303: invokevirtual toString : ()Ljava/lang/String;
    //   306: iconst_0
    //   307: iload #5
    //   309: invokevirtual substring : (II)Ljava/lang/String;
    //   312: invokevirtual append : (Ljava/lang/String;)Ljava/lang/StringBuilder;
    //   315: swap
    //   316: invokevirtual append : (C)Ljava/lang/StringBuilder;
    //   319: pop2
    //   320: goto -> 386
    //   323: new io/undertow/util/BadRequestException
    //   326: dup
    //   327: invokespecial <init> : ()V
    //   330: athrow
    //   331: iconst_0
    //   332: istore #4
    //   334: aload #8
    //   336: arraylength
    //   337: iload #5
    //   339: if_icmpeq -> 369
    //   342: new io/undertow/util/HttpString
    //   345: dup
    //   346: aload #8
    //   348: iconst_0
    //   349: iload #5
    //   351: invokespecial <init> : ([BII)V
    //   354: aload_2
    //   355: swap
    //   356: putfield nextHeader : Lio/undertow/util/HttpString;
    //   359: pop
    //   360: pop
    //   361: aload_2
    //   362: iconst_5
    //   363: putfield state : I
    //   366: goto -> 200
    //   369: aload #6
    //   371: aload_2
    //   372: swap
    //   373: putfield nextHeader : Lio/undertow/util/HttpString;
    //   376: pop
    //   377: pop
    //   378: aload_2
    //   379: iconst_5
    //   380: putfield state : I
    //   383: goto -> 200
    //   386: aload_1
    //   387: invokevirtual hasRemaining : ()Z
    //   390: ifeq -> 174
    //   393: aload_1
    //   394: invokevirtual get : ()B
    //   397: dup
    //   398: bipush #58
    //   400: if_icmpeq -> 443
    //   403: dup
    //   404: bipush #32
    //   406: if_icmpeq -> 443
    //   409: dup
    //   410: bipush #13
    //   412: if_icmpeq -> 443
    //   415: dup
    //   416: bipush #10
    //   418: if_icmpeq -> 443
    //   421: aload #7
    //   423: swap
    //   424: invokevirtual append : (C)Ljava/lang/StringBuilder;
    //   427: pop
    //   428: aload_1
    //   429: invokevirtual hasRemaining : ()Z
    //   432: ifne -> 386
    //   435: aload_2
    //   436: iload #4
    //   438: putfield parseState : I
    //   441: iconst_0
    //   442: return
    //   443: aload #7
    //   445: invokevirtual toString : ()Ljava/lang/String;
    //   448: new io/undertow/util/HttpString
    //   451: dup_x1
    //   452: swap
    //   453: invokespecial <init> : (Ljava/lang/String;)V
    //   456: aload_2
    //   457: swap
    //   458: putfield nextHeader : Lio/undertow/util/HttpString;
    //   461: pop
    //   462: aload_2
    //   463: iconst_5
    //   464: putfield state : I
    //   467: goto -> 200
    //   470: pop
    //   471: iconst_0
    //   472: istore #5
    //   474: aconst_null
    //   475: astore #6
    //   477: aconst_null
    //   478: astore #8
    //   480: aload_2
    //   481: getfield leftOver : B
    //   484: dup
    //   485: ifne -> 503
    //   488: pop
    //   489: aload_1
    //   490: invokevirtual hasRemaining : ()Z
    //   493: ifeq -> 174
    //   496: aload_1
    //   497: invokevirtual get : ()B
    //   500: goto -> 508
    //   503: aload_2
    //   504: iconst_0
    //   505: putfield leftOver : B
    //   508: dup
    //   509: bipush #65
    //   511: if_icmpeq -> 676
    //   514: dup
    //   515: bipush #67
    //   517: if_icmpeq -> 691
    //   520: dup
    //   521: bipush #68
    //   523: if_icmpeq -> 639
    //   526: dup
    //   527: bipush #69
    //   529: if_icmpeq -> 706
    //   532: dup
    //   533: bipush #76
    //   535: if_icmpeq -> 722
    //   538: dup
    //   539: bipush #80
    //   541: if_icmpeq -> 631
    //   544: dup
    //   545: bipush #82
    //   547: if_icmpeq -> 714
    //   550: dup
    //   551: bipush #83
    //   553: if_icmpeq -> 698
    //   556: dup
    //   557: bipush #84
    //   559: if_icmpeq -> 660
    //   562: dup
    //   563: bipush #86
    //   565: if_icmpeq -> 668
    //   568: dup
    //   569: bipush #87
    //   571: if_icmpeq -> 683
    //   574: dup
    //   575: bipush #58
    //   577: if_icmpeq -> 616
    //   580: dup
    //   581: bipush #13
    //   583: if_icmpeq -> 616
    //   586: dup
    //   587: bipush #10
    //   589: if_icmpeq -> 616
    //   592: dup
    //   593: bipush #32
    //   595: if_icmpeq -> 616
    //   598: iconst_m1
    //   599: istore #4
    //   601: aload #7
    //   603: ldc ''
    //   605: invokevirtual append : (Ljava/lang/String;)Ljava/lang/StringBuilder;
    //   608: swap
    //   609: invokevirtual append : (C)Ljava/lang/StringBuilder;
    //   612: pop
    //   613: goto -> 386
    //   616: bipush #10
    //   618: if_icmpeq -> 730
    //   621: aload_1
    //   622: invokevirtual hasRemaining : ()Z
    //   625: ifeq -> 174
    //   628: goto -> 480
    //   631: pop
    //   632: bipush #13
    //   634: istore #4
    //   636: goto -> 2136
    //   639: pop
    //   640: bipush #-2
    //   642: istore #4
    //   644: getstatic io/undertow/client/http/HttpResponseParser$$generated.HTTP_STRING_198 : Lio/undertow/util/HttpString;
    //   647: astore #6
    //   649: getstatic io/undertow/client/http/HttpResponseParser$$generated.STATE_BYTES_197 : [B
    //   652: astore #8
    //   654: iconst_1
    //   655: istore #5
    //   657: goto -> 228
    //   660: pop
    //   661: bipush #19
    //   663: istore #4
    //   665: goto -> 2793
    //   668: pop
    //   669: bipush #22
    //   671: istore #4
    //   673: goto -> 3088
    //   676: pop
    //   677: iconst_1
    //   678: istore #4
    //   680: goto -> 736
    //   683: pop
    //   684: bipush #23
    //   686: istore #4
    //   688: goto -> 3213
    //   691: pop
    //   692: iconst_2
    //   693: istore #4
    //   695: goto -> 860
    //   698: pop
    //   699: bipush #17
    //   701: istore #4
    //   703: goto -> 2556
    //   706: pop
    //   707: bipush #11
    //   709: istore #4
    //   711: goto -> 1886
    //   714: pop
    //   715: bipush #15
    //   717: istore #4
    //   719: goto -> 2346
    //   722: pop
    //   723: bipush #12
    //   725: istore #4
    //   727: goto -> 2011
    //   730: aload_2
    //   731: invokevirtual parseComplete : ()V
    //   734: iconst_0
    //   735: return
    //   736: aload_1
    //   737: invokevirtual hasRemaining : ()Z
    //   740: ifeq -> 174
    //   743: aload_1
    //   744: invokevirtual get : ()B
    //   747: dup
    //   748: bipush #99
    //   750: if_icmpeq -> 818
    //   753: dup
    //   754: bipush #103
    //   756: if_icmpeq -> 839
    //   759: dup
    //   760: bipush #58
    //   762: if_icmpeq -> 801
    //   765: dup
    //   766: bipush #13
    //   768: if_icmpeq -> 801
    //   771: dup
    //   772: bipush #10
    //   774: if_icmpeq -> 801
    //   777: dup
    //   778: bipush #32
    //   780: if_icmpeq -> 801
    //   783: iconst_m1
    //   784: istore #4
    //   786: aload #7
    //   788: ldc 'A'
    //   790: invokevirtual append : (Ljava/lang/String;)Ljava/lang/StringBuilder;
    //   793: swap
    //   794: invokevirtual append : (C)Ljava/lang/StringBuilder;
    //   797: pop
    //   798: goto -> 386
    //   801: getstatic io/undertow/client/http/HttpResponseParser$$generated.HTTP_STRING_21 : Lio/undertow/util/HttpString;
    //   804: aload_2
    //   805: swap
    //   806: putfield nextHeader : Lio/undertow/util/HttpString;
    //   809: pop
    //   810: aload_2
    //   811: iconst_5
    //   812: putfield state : I
    //   815: goto -> 200
    //   818: pop
    //   819: bipush #-2
    //   821: istore #4
    //   823: getstatic io/undertow/client/http/HttpResponseParser$$generated.HTTP_STRING_23 : Lio/undertow/util/HttpString;
    //   826: astore #6
    //   828: getstatic io/undertow/client/http/HttpResponseParser$$generated.STATE_BYTES_22 : [B
    //   831: astore #8
    //   833: iconst_2
    //   834: istore #5
    //   836: goto -> 228
    //   839: pop
    //   840: bipush #-2
    //   842: istore #4
    //   844: getstatic io/undertow/client/http/HttpResponseParser$$generated.HTTP_STRING_47 : Lio/undertow/util/HttpString;
    //   847: astore #6
    //   849: getstatic io/undertow/client/http/HttpResponseParser$$generated.STATE_BYTES_46 : [B
    //   852: astore #8
    //   854: iconst_2
    //   855: istore #5
    //   857: goto -> 228
    //   860: aload_1
    //   861: invokevirtual hasRemaining : ()Z
    //   864: ifeq -> 174
    //   867: aload_1
    //   868: invokevirtual get : ()B
    //   871: dup
    //   872: bipush #97
    //   874: if_icmpeq -> 950
    //   877: dup
    //   878: bipush #111
    //   880: if_icmpeq -> 943
    //   883: dup
    //   884: bipush #58
    //   886: if_icmpeq -> 926
    //   889: dup
    //   890: bipush #13
    //   892: if_icmpeq -> 926
    //   895: dup
    //   896: bipush #10
    //   898: if_icmpeq -> 926
    //   901: dup
    //   902: bipush #32
    //   904: if_icmpeq -> 926
    //   907: iconst_m1
    //   908: istore #4
    //   910: aload #7
    //   912: ldc_w 'C'
    //   915: invokevirtual append : (Ljava/lang/String;)Ljava/lang/StringBuilder;
    //   918: swap
    //   919: invokevirtual append : (C)Ljava/lang/StringBuilder;
    //   922: pop
    //   923: goto -> 386
    //   926: getstatic io/undertow/client/http/HttpResponseParser$$generated.HTTP_STRING_50 : Lio/undertow/util/HttpString;
    //   929: aload_2
    //   930: swap
    //   931: putfield nextHeader : Lio/undertow/util/HttpString;
    //   934: pop
    //   935: aload_2
    //   936: iconst_5
    //   937: putfield state : I
    //   940: goto -> 200
    //   943: pop
    //   944: iconst_3
    //   945: istore #4
    //   947: goto -> 971
    //   950: pop
    //   951: bipush #-2
    //   953: istore #4
    //   955: getstatic io/undertow/client/http/HttpResponseParser$$generated.HTTP_STRING_52 : Lio/undertow/util/HttpString;
    //   958: astore #6
    //   960: getstatic io/undertow/client/http/HttpResponseParser$$generated.STATE_BYTES_51 : [B
    //   963: astore #8
    //   965: iconst_2
    //   966: istore #5
    //   968: goto -> 228
    //   971: aload_1
    //   972: invokevirtual hasRemaining : ()Z
    //   975: ifeq -> 174
    //   978: aload_1
    //   979: invokevirtual get : ()B
    //   982: dup
    //   983: bipush #110
    //   985: if_icmpeq -> 1048
    //   988: dup
    //   989: bipush #58
    //   991: if_icmpeq -> 1031
    //   994: dup
    //   995: bipush #13
    //   997: if_icmpeq -> 1031
    //   1000: dup
    //   1001: bipush #10
    //   1003: if_icmpeq -> 1031
    //   1006: dup
    //   1007: bipush #32
    //   1009: if_icmpeq -> 1031
    //   1012: iconst_m1
    //   1013: istore #4
    //   1015: aload #7
    //   1017: ldc_w 'Co'
    //   1020: invokevirtual append : (Ljava/lang/String;)Ljava/lang/StringBuilder;
    //   1023: swap
    //   1024: invokevirtual append : (C)Ljava/lang/StringBuilder;
    //   1027: pop
    //   1028: goto -> 386
    //   1031: getstatic io/undertow/client/http/HttpResponseParser$$generated.HTTP_STRING_75 : Lio/undertow/util/HttpString;
    //   1034: aload_2
    //   1035: swap
    //   1036: putfield nextHeader : Lio/undertow/util/HttpString;
    //   1039: pop
    //   1040: aload_2
    //   1041: iconst_5
    //   1042: putfield state : I
    //   1045: goto -> 200
    //   1048: pop
    //   1049: iconst_4
    //   1050: istore #4
    //   1052: goto -> 1055
    //   1055: aload_1
    //   1056: invokevirtual hasRemaining : ()Z
    //   1059: ifeq -> 174
    //   1062: aload_1
    //   1063: invokevirtual get : ()B
    //   1066: dup
    //   1067: bipush #110
    //   1069: if_icmpeq -> 1145
    //   1072: dup
    //   1073: bipush #116
    //   1075: if_icmpeq -> 1138
    //   1078: dup
    //   1079: bipush #58
    //   1081: if_icmpeq -> 1121
    //   1084: dup
    //   1085: bipush #13
    //   1087: if_icmpeq -> 1121
    //   1090: dup
    //   1091: bipush #10
    //   1093: if_icmpeq -> 1121
    //   1096: dup
    //   1097: bipush #32
    //   1099: if_icmpeq -> 1121
    //   1102: iconst_m1
    //   1103: istore #4
    //   1105: aload #7
    //   1107: ldc_w 'Con'
    //   1110: invokevirtual append : (Ljava/lang/String;)Ljava/lang/StringBuilder;
    //   1113: swap
    //   1114: invokevirtual append : (C)Ljava/lang/StringBuilder;
    //   1117: pop
    //   1118: goto -> 386
    //   1121: getstatic io/undertow/client/http/HttpResponseParser$$generated.HTTP_STRING_76 : Lio/undertow/util/HttpString;
    //   1124: aload_2
    //   1125: swap
    //   1126: putfield nextHeader : Lio/undertow/util/HttpString;
    //   1129: pop
    //   1130: aload_2
    //   1131: iconst_5
    //   1132: putfield state : I
    //   1135: goto -> 200
    //   1138: pop
    //   1139: iconst_5
    //   1140: istore #4
    //   1142: goto -> 1166
    //   1145: pop
    //   1146: bipush #-2
    //   1148: istore #4
    //   1150: getstatic io/undertow/client/http/HttpResponseParser$$generated.HTTP_STRING_78 : Lio/undertow/util/HttpString;
    //   1153: astore #6
    //   1155: getstatic io/undertow/client/http/HttpResponseParser$$generated.STATE_BYTES_77 : [B
    //   1158: astore #8
    //   1160: iconst_4
    //   1161: istore #5
    //   1163: goto -> 228
    //   1166: aload_1
    //   1167: invokevirtual hasRemaining : ()Z
    //   1170: ifeq -> 174
    //   1173: aload_1
    //   1174: invokevirtual get : ()B
    //   1177: dup
    //   1178: bipush #101
    //   1180: if_icmpeq -> 1243
    //   1183: dup
    //   1184: bipush #58
    //   1186: if_icmpeq -> 1226
    //   1189: dup
    //   1190: bipush #13
    //   1192: if_icmpeq -> 1226
    //   1195: dup
    //   1196: bipush #10
    //   1198: if_icmpeq -> 1226
    //   1201: dup
    //   1202: bipush #32
    //   1204: if_icmpeq -> 1226
    //   1207: iconst_m1
    //   1208: istore #4
    //   1210: aload #7
    //   1212: ldc_w 'Cont'
    //   1215: invokevirtual append : (Ljava/lang/String;)Ljava/lang/StringBuilder;
    //   1218: swap
    //   1219: invokevirtual append : (C)Ljava/lang/StringBuilder;
    //   1222: pop
    //   1223: goto -> 386
    //   1226: getstatic io/undertow/client/http/HttpResponseParser$$generated.HTTP_STRING_91 : Lio/undertow/util/HttpString;
    //   1229: aload_2
    //   1230: swap
    //   1231: putfield nextHeader : Lio/undertow/util/HttpString;
    //   1234: pop
    //   1235: aload_2
    //   1236: iconst_5
    //   1237: putfield state : I
    //   1240: goto -> 200
    //   1243: pop
    //   1244: bipush #6
    //   1246: istore #4
    //   1248: goto -> 1251
    //   1251: aload_1
    //   1252: invokevirtual hasRemaining : ()Z
    //   1255: ifeq -> 174
    //   1258: aload_1
    //   1259: invokevirtual get : ()B
    //   1262: dup
    //   1263: bipush #110
    //   1265: if_icmpeq -> 1328
    //   1268: dup
    //   1269: bipush #58
    //   1271: if_icmpeq -> 1311
    //   1274: dup
    //   1275: bipush #13
    //   1277: if_icmpeq -> 1311
    //   1280: dup
    //   1281: bipush #10
    //   1283: if_icmpeq -> 1311
    //   1286: dup
    //   1287: bipush #32
    //   1289: if_icmpeq -> 1311
    //   1292: iconst_m1
    //   1293: istore #4
    //   1295: aload #7
    //   1297: ldc_w 'Conte'
    //   1300: invokevirtual append : (Ljava/lang/String;)Ljava/lang/StringBuilder;
    //   1303: swap
    //   1304: invokevirtual append : (C)Ljava/lang/StringBuilder;
    //   1307: pop
    //   1308: goto -> 386
    //   1311: getstatic io/undertow/client/http/HttpResponseParser$$generated.HTTP_STRING_92 : Lio/undertow/util/HttpString;
    //   1314: aload_2
    //   1315: swap
    //   1316: putfield nextHeader : Lio/undertow/util/HttpString;
    //   1319: pop
    //   1320: aload_2
    //   1321: iconst_5
    //   1322: putfield state : I
    //   1325: goto -> 200
    //   1328: pop
    //   1329: bipush #7
    //   1331: istore #4
    //   1333: goto -> 1336
    //   1336: aload_1
    //   1337: invokevirtual hasRemaining : ()Z
    //   1340: ifeq -> 174
    //   1343: aload_1
    //   1344: invokevirtual get : ()B
    //   1347: dup
    //   1348: bipush #116
    //   1350: if_icmpeq -> 1413
    //   1353: dup
    //   1354: bipush #58
    //   1356: if_icmpeq -> 1396
    //   1359: dup
    //   1360: bipush #13
    //   1362: if_icmpeq -> 1396
    //   1365: dup
    //   1366: bipush #10
    //   1368: if_icmpeq -> 1396
    //   1371: dup
    //   1372: bipush #32
    //   1374: if_icmpeq -> 1396
    //   1377: iconst_m1
    //   1378: istore #4
    //   1380: aload #7
    //   1382: ldc_w 'Conten'
    //   1385: invokevirtual append : (Ljava/lang/String;)Ljava/lang/StringBuilder;
    //   1388: swap
    //   1389: invokevirtual append : (C)Ljava/lang/StringBuilder;
    //   1392: pop
    //   1393: goto -> 386
    //   1396: getstatic io/undertow/client/http/HttpResponseParser$$generated.HTTP_STRING_93 : Lio/undertow/util/HttpString;
    //   1399: aload_2
    //   1400: swap
    //   1401: putfield nextHeader : Lio/undertow/util/HttpString;
    //   1404: pop
    //   1405: aload_2
    //   1406: iconst_5
    //   1407: putfield state : I
    //   1410: goto -> 200
    //   1413: pop
    //   1414: bipush #8
    //   1416: istore #4
    //   1418: goto -> 1421
    //   1421: aload_1
    //   1422: invokevirtual hasRemaining : ()Z
    //   1425: ifeq -> 174
    //   1428: aload_1
    //   1429: invokevirtual get : ()B
    //   1432: dup
    //   1433: bipush #45
    //   1435: if_icmpeq -> 1498
    //   1438: dup
    //   1439: bipush #58
    //   1441: if_icmpeq -> 1481
    //   1444: dup
    //   1445: bipush #13
    //   1447: if_icmpeq -> 1481
    //   1450: dup
    //   1451: bipush #10
    //   1453: if_icmpeq -> 1481
    //   1456: dup
    //   1457: bipush #32
    //   1459: if_icmpeq -> 1481
    //   1462: iconst_m1
    //   1463: istore #4
    //   1465: aload #7
    //   1467: ldc_w 'Content'
    //   1470: invokevirtual append : (Ljava/lang/String;)Ljava/lang/StringBuilder;
    //   1473: swap
    //   1474: invokevirtual append : (C)Ljava/lang/StringBuilder;
    //   1477: pop
    //   1478: goto -> 386
    //   1481: getstatic io/undertow/client/http/HttpResponseParser$$generated.HTTP_STRING_94 : Lio/undertow/util/HttpString;
    //   1484: aload_2
    //   1485: swap
    //   1486: putfield nextHeader : Lio/undertow/util/HttpString;
    //   1489: pop
    //   1490: aload_2
    //   1491: iconst_5
    //   1492: putfield state : I
    //   1495: goto -> 200
    //   1498: pop
    //   1499: bipush #9
    //   1501: istore #4
    //   1503: goto -> 1506
    //   1506: aload_1
    //   1507: invokevirtual hasRemaining : ()Z
    //   1510: ifeq -> 174
    //   1513: aload_1
    //   1514: invokevirtual get : ()B
    //   1517: dup
    //   1518: bipush #68
    //   1520: if_icmpeq -> 1679
    //   1523: dup
    //   1524: bipush #69
    //   1526: if_icmpeq -> 1701
    //   1529: dup
    //   1530: bipush #76
    //   1532: if_icmpeq -> 1723
    //   1535: dup
    //   1536: bipush #77
    //   1538: if_icmpeq -> 1635
    //   1541: dup
    //   1542: bipush #82
    //   1544: if_icmpeq -> 1657
    //   1547: dup
    //   1548: bipush #84
    //   1550: if_icmpeq -> 1613
    //   1553: dup
    //   1554: bipush #58
    //   1556: if_icmpeq -> 1596
    //   1559: dup
    //   1560: bipush #13
    //   1562: if_icmpeq -> 1596
    //   1565: dup
    //   1566: bipush #10
    //   1568: if_icmpeq -> 1596
    //   1571: dup
    //   1572: bipush #32
    //   1574: if_icmpeq -> 1596
    //   1577: iconst_m1
    //   1578: istore #4
    //   1580: aload #7
    //   1582: ldc_w 'Content-'
    //   1585: invokevirtual append : (Ljava/lang/String;)Ljava/lang/StringBuilder;
    //   1588: swap
    //   1589: invokevirtual append : (C)Ljava/lang/StringBuilder;
    //   1592: pop
    //   1593: goto -> 386
    //   1596: getstatic io/undertow/client/http/HttpResponseParser$$generated.HTTP_STRING_95 : Lio/undertow/util/HttpString;
    //   1599: aload_2
    //   1600: swap
    //   1601: putfield nextHeader : Lio/undertow/util/HttpString;
    //   1604: pop
    //   1605: aload_2
    //   1606: iconst_5
    //   1607: putfield state : I
    //   1610: goto -> 200
    //   1613: pop
    //   1614: bipush #-2
    //   1616: istore #4
    //   1618: getstatic io/undertow/client/http/HttpResponseParser$$generated.HTTP_STRING_190 : Lio/undertow/util/HttpString;
    //   1621: astore #6
    //   1623: getstatic io/undertow/client/http/HttpResponseParser$$generated.STATE_BYTES_189 : [B
    //   1626: astore #8
    //   1628: bipush #9
    //   1630: istore #5
    //   1632: goto -> 228
    //   1635: pop
    //   1636: bipush #-2
    //   1638: istore #4
    //   1640: getstatic io/undertow/client/http/HttpResponseParser$$generated.HTTP_STRING_174 : Lio/undertow/util/HttpString;
    //   1643: astore #6
    //   1645: getstatic io/undertow/client/http/HttpResponseParser$$generated.STATE_BYTES_173 : [B
    //   1648: astore #8
    //   1650: bipush #9
    //   1652: istore #5
    //   1654: goto -> 228
    //   1657: pop
    //   1658: bipush #-2
    //   1660: istore #4
    //   1662: getstatic io/undertow/client/http/HttpResponseParser$$generated.HTTP_STRING_180 : Lio/undertow/util/HttpString;
    //   1665: astore #6
    //   1667: getstatic io/undertow/client/http/HttpResponseParser$$generated.STATE_BYTES_179 : [B
    //   1670: astore #8
    //   1672: bipush #9
    //   1674: istore #5
    //   1676: goto -> 228
    //   1679: pop
    //   1680: bipush #-2
    //   1682: istore #4
    //   1684: getstatic io/undertow/client/http/HttpResponseParser$$generated.HTTP_STRING_97 : Lio/undertow/util/HttpString;
    //   1687: astore #6
    //   1689: getstatic io/undertow/client/http/HttpResponseParser$$generated.STATE_BYTES_96 : [B
    //   1692: astore #8
    //   1694: bipush #9
    //   1696: istore #5
    //   1698: goto -> 228
    //   1701: pop
    //   1702: bipush #-2
    //   1704: istore #4
    //   1706: getstatic io/undertow/client/http/HttpResponseParser$$generated.HTTP_STRING_119 : Lio/undertow/util/HttpString;
    //   1709: astore #6
    //   1711: getstatic io/undertow/client/http/HttpResponseParser$$generated.STATE_BYTES_118 : [B
    //   1714: astore #8
    //   1716: bipush #9
    //   1718: istore #5
    //   1720: goto -> 228
    //   1723: pop
    //   1724: bipush #10
    //   1726: istore #4
    //   1728: goto -> 1731
    //   1731: aload_1
    //   1732: invokevirtual hasRemaining : ()Z
    //   1735: ifeq -> 174
    //   1738: aload_1
    //   1739: invokevirtual get : ()B
    //   1742: dup
    //   1743: bipush #97
    //   1745: if_icmpeq -> 1820
    //   1748: dup
    //   1749: bipush #101
    //   1751: if_icmpeq -> 1864
    //   1754: dup
    //   1755: bipush #111
    //   1757: if_icmpeq -> 1842
    //   1760: dup
    //   1761: bipush #58
    //   1763: if_icmpeq -> 1803
    //   1766: dup
    //   1767: bipush #13
    //   1769: if_icmpeq -> 1803
    //   1772: dup
    //   1773: bipush #10
    //   1775: if_icmpeq -> 1803
    //   1778: dup
    //   1779: bipush #32
    //   1781: if_icmpeq -> 1803
    //   1784: iconst_m1
    //   1785: istore #4
    //   1787: aload #7
    //   1789: ldc_w 'Content-L'
    //   1792: invokevirtual append : (Ljava/lang/String;)Ljava/lang/StringBuilder;
    //   1795: swap
    //   1796: invokevirtual append : (C)Ljava/lang/StringBuilder;
    //   1799: pop
    //   1800: goto -> 386
    //   1803: getstatic io/undertow/client/http/HttpResponseParser$$generated.HTTP_STRING_134 : Lio/undertow/util/HttpString;
    //   1806: aload_2
    //   1807: swap
    //   1808: putfield nextHeader : Lio/undertow/util/HttpString;
    //   1811: pop
    //   1812: aload_2
    //   1813: iconst_5
    //   1814: putfield state : I
    //   1817: goto -> 200
    //   1820: pop
    //   1821: bipush #-2
    //   1823: istore #4
    //   1825: getstatic io/undertow/client/http/HttpResponseParser$$generated.HTTP_STRING_136 : Lio/undertow/util/HttpString;
    //   1828: astore #6
    //   1830: getstatic io/undertow/client/http/HttpResponseParser$$generated.STATE_BYTES_135 : [B
    //   1833: astore #8
    //   1835: bipush #10
    //   1837: istore #5
    //   1839: goto -> 228
    //   1842: pop
    //   1843: bipush #-2
    //   1845: istore #4
    //   1847: getstatic io/undertow/client/http/HttpResponseParser$$generated.HTTP_STRING_160 : Lio/undertow/util/HttpString;
    //   1850: astore #6
    //   1852: getstatic io/undertow/client/http/HttpResponseParser$$generated.STATE_BYTES_159 : [B
    //   1855: astore #8
    //   1857: bipush #10
    //   1859: istore #5
    //   1861: goto -> 228
    //   1864: pop
    //   1865: bipush #-2
    //   1867: istore #4
    //   1869: getstatic io/undertow/client/http/HttpResponseParser$$generated.HTTP_STRING_150 : Lio/undertow/util/HttpString;
    //   1872: astore #6
    //   1874: getstatic io/undertow/client/http/HttpResponseParser$$generated.STATE_BYTES_149 : [B
    //   1877: astore #8
    //   1879: bipush #10
    //   1881: istore #5
    //   1883: goto -> 228
    //   1886: aload_1
    //   1887: invokevirtual hasRemaining : ()Z
    //   1890: ifeq -> 174
    //   1893: aload_1
    //   1894: invokevirtual get : ()B
    //   1897: dup
    //   1898: bipush #120
    //   1900: if_icmpeq -> 1990
    //   1903: dup
    //   1904: bipush #84
    //   1906: if_icmpeq -> 1969
    //   1909: dup
    //   1910: bipush #58
    //   1912: if_icmpeq -> 1952
    //   1915: dup
    //   1916: bipush #13
    //   1918: if_icmpeq -> 1952
    //   1921: dup
    //   1922: bipush #10
    //   1924: if_icmpeq -> 1952
    //   1927: dup
    //   1928: bipush #32
    //   1930: if_icmpeq -> 1952
    //   1933: iconst_m1
    //   1934: istore #4
    //   1936: aload #7
    //   1938: ldc_w 'E'
    //   1941: invokevirtual append : (Ljava/lang/String;)Ljava/lang/StringBuilder;
    //   1944: swap
    //   1945: invokevirtual append : (C)Ljava/lang/StringBuilder;
    //   1948: pop
    //   1949: goto -> 386
    //   1952: getstatic io/undertow/client/http/HttpResponseParser$$generated.HTTP_STRING_205 : Lio/undertow/util/HttpString;
    //   1955: aload_2
    //   1956: swap
    //   1957: putfield nextHeader : Lio/undertow/util/HttpString;
    //   1960: pop
    //   1961: aload_2
    //   1962: iconst_5
    //   1963: putfield state : I
    //   1966: goto -> 200
    //   1969: pop
    //   1970: bipush #-2
    //   1972: istore #4
    //   1974: getstatic io/undertow/client/http/HttpResponseParser$$generated.HTTP_STRING_219 : Lio/undertow/util/HttpString;
    //   1977: astore #6
    //   1979: getstatic io/undertow/client/http/HttpResponseParser$$generated.STATE_BYTES_218 : [B
    //   1982: astore #8
    //   1984: iconst_2
    //   1985: istore #5
    //   1987: goto -> 228
    //   1990: pop
    //   1991: bipush #-2
    //   1993: istore #4
    //   1995: getstatic io/undertow/client/http/HttpResponseParser$$generated.HTTP_STRING_207 : Lio/undertow/util/HttpString;
    //   1998: astore #6
    //   2000: getstatic io/undertow/client/http/HttpResponseParser$$generated.STATE_BYTES_206 : [B
    //   2003: astore #8
    //   2005: iconst_2
    //   2006: istore #5
    //   2008: goto -> 228
    //   2011: aload_1
    //   2012: invokevirtual hasRemaining : ()Z
    //   2015: ifeq -> 174
    //   2018: aload_1
    //   2019: invokevirtual get : ()B
    //   2022: dup
    //   2023: bipush #97
    //   2025: if_icmpeq -> 2094
    //   2028: dup
    //   2029: bipush #111
    //   2031: if_icmpeq -> 2115
    //   2034: dup
    //   2035: bipush #58
    //   2037: if_icmpeq -> 2077
    //   2040: dup
    //   2041: bipush #13
    //   2043: if_icmpeq -> 2077
    //   2046: dup
    //   2047: bipush #10
    //   2049: if_icmpeq -> 2077
    //   2052: dup
    //   2053: bipush #32
    //   2055: if_icmpeq -> 2077
    //   2058: iconst_m1
    //   2059: istore #4
    //   2061: aload #7
    //   2063: ldc_w 'L'
    //   2066: invokevirtual append : (Ljava/lang/String;)Ljava/lang/StringBuilder;
    //   2069: swap
    //   2070: invokevirtual append : (C)Ljava/lang/StringBuilder;
    //   2073: pop
    //   2074: goto -> 386
    //   2077: getstatic io/undertow/client/http/HttpResponseParser$$generated.HTTP_STRING_224 : Lio/undertow/util/HttpString;
    //   2080: aload_2
    //   2081: swap
    //   2082: putfield nextHeader : Lio/undertow/util/HttpString;
    //   2085: pop
    //   2086: aload_2
    //   2087: iconst_5
    //   2088: putfield state : I
    //   2091: goto -> 200
    //   2094: pop
    //   2095: bipush #-2
    //   2097: istore #4
    //   2099: getstatic io/undertow/client/http/HttpResponseParser$$generated.HTTP_STRING_226 : Lio/undertow/util/HttpString;
    //   2102: astore #6
    //   2104: getstatic io/undertow/client/http/HttpResponseParser$$generated.STATE_BYTES_225 : [B
    //   2107: astore #8
    //   2109: iconst_2
    //   2110: istore #5
    //   2112: goto -> 228
    //   2115: pop
    //   2116: bipush #-2
    //   2118: istore #4
    //   2120: getstatic io/undertow/client/http/HttpResponseParser$$generated.HTTP_STRING_250 : Lio/undertow/util/HttpString;
    //   2123: astore #6
    //   2125: getstatic io/undertow/client/http/HttpResponseParser$$generated.STATE_BYTES_249 : [B
    //   2128: astore #8
    //   2130: iconst_2
    //   2131: istore #5
    //   2133: goto -> 228
    //   2136: aload_1
    //   2137: invokevirtual hasRemaining : ()Z
    //   2140: ifeq -> 174
    //   2143: aload_1
    //   2144: invokevirtual get : ()B
    //   2147: dup
    //   2148: bipush #114
    //   2150: if_icmpeq -> 2213
    //   2153: dup
    //   2154: bipush #58
    //   2156: if_icmpeq -> 2196
    //   2159: dup
    //   2160: bipush #13
    //   2162: if_icmpeq -> 2196
    //   2165: dup
    //   2166: bipush #10
    //   2168: if_icmpeq -> 2196
    //   2171: dup
    //   2172: bipush #32
    //   2174: if_icmpeq -> 2196
    //   2177: iconst_m1
    //   2178: istore #4
    //   2180: aload #7
    //   2182: ldc_w 'P'
    //   2185: invokevirtual append : (Ljava/lang/String;)Ljava/lang/StringBuilder;
    //   2188: swap
    //   2189: invokevirtual append : (C)Ljava/lang/StringBuilder;
    //   2192: pop
    //   2193: goto -> 386
    //   2196: getstatic io/undertow/client/http/HttpResponseParser$$generated.HTTP_STRING_263 : Lio/undertow/util/HttpString;
    //   2199: aload_2
    //   2200: swap
    //   2201: putfield nextHeader : Lio/undertow/util/HttpString;
    //   2204: pop
    //   2205: aload_2
    //   2206: iconst_5
    //   2207: putfield state : I
    //   2210: goto -> 200
    //   2213: pop
    //   2214: bipush #14
    //   2216: istore #4
    //   2218: goto -> 2221
    //   2221: aload_1
    //   2222: invokevirtual hasRemaining : ()Z
    //   2225: ifeq -> 174
    //   2228: aload_1
    //   2229: invokevirtual get : ()B
    //   2232: dup
    //   2233: bipush #97
    //   2235: if_icmpeq -> 2304
    //   2238: dup
    //   2239: bipush #111
    //   2241: if_icmpeq -> 2325
    //   2244: dup
    //   2245: bipush #58
    //   2247: if_icmpeq -> 2287
    //   2250: dup
    //   2251: bipush #13
    //   2253: if_icmpeq -> 2287
    //   2256: dup
    //   2257: bipush #10
    //   2259: if_icmpeq -> 2287
    //   2262: dup
    //   2263: bipush #32
    //   2265: if_icmpeq -> 2287
    //   2268: iconst_m1
    //   2269: istore #4
    //   2271: aload #7
    //   2273: ldc_w 'Pr'
    //   2276: invokevirtual append : (Ljava/lang/String;)Ljava/lang/StringBuilder;
    //   2279: swap
    //   2280: invokevirtual append : (C)Ljava/lang/StringBuilder;
    //   2283: pop
    //   2284: goto -> 386
    //   2287: getstatic io/undertow/client/http/HttpResponseParser$$generated.HTTP_STRING_264 : Lio/undertow/util/HttpString;
    //   2290: aload_2
    //   2291: swap
    //   2292: putfield nextHeader : Lio/undertow/util/HttpString;
    //   2295: pop
    //   2296: aload_2
    //   2297: iconst_5
    //   2298: putfield state : I
    //   2301: goto -> 200
    //   2304: pop
    //   2305: bipush #-2
    //   2307: istore #4
    //   2309: getstatic io/undertow/client/http/HttpResponseParser$$generated.HTTP_STRING_266 : Lio/undertow/util/HttpString;
    //   2312: astore #6
    //   2314: getstatic io/undertow/client/http/HttpResponseParser$$generated.STATE_BYTES_265 : [B
    //   2317: astore #8
    //   2319: iconst_3
    //   2320: istore #5
    //   2322: goto -> 228
    //   2325: pop
    //   2326: bipush #-2
    //   2328: istore #4
    //   2330: getstatic io/undertow/client/http/HttpResponseParser$$generated.HTTP_STRING_274 : Lio/undertow/util/HttpString;
    //   2333: astore #6
    //   2335: getstatic io/undertow/client/http/HttpResponseParser$$generated.STATE_BYTES_273 : [B
    //   2338: astore #8
    //   2340: iconst_3
    //   2341: istore #5
    //   2343: goto -> 228
    //   2346: aload_1
    //   2347: invokevirtual hasRemaining : ()Z
    //   2350: ifeq -> 174
    //   2353: aload_1
    //   2354: invokevirtual get : ()B
    //   2357: dup
    //   2358: bipush #101
    //   2360: if_icmpeq -> 2423
    //   2363: dup
    //   2364: bipush #58
    //   2366: if_icmpeq -> 2406
    //   2369: dup
    //   2370: bipush #13
    //   2372: if_icmpeq -> 2406
    //   2375: dup
    //   2376: bipush #10
    //   2378: if_icmpeq -> 2406
    //   2381: dup
    //   2382: bipush #32
    //   2384: if_icmpeq -> 2406
    //   2387: iconst_m1
    //   2388: istore #4
    //   2390: aload #7
    //   2392: ldc_w 'R'
    //   2395: invokevirtual append : (Ljava/lang/String;)Ljava/lang/StringBuilder;
    //   2398: swap
    //   2399: invokevirtual append : (C)Ljava/lang/StringBuilder;
    //   2402: pop
    //   2403: goto -> 386
    //   2406: getstatic io/undertow/client/http/HttpResponseParser$$generated.HTTP_STRING_305 : Lio/undertow/util/HttpString;
    //   2409: aload_2
    //   2410: swap
    //   2411: putfield nextHeader : Lio/undertow/util/HttpString;
    //   2414: pop
    //   2415: aload_2
    //   2416: iconst_5
    //   2417: putfield state : I
    //   2420: goto -> 200
    //   2423: pop
    //   2424: bipush #16
    //   2426: istore #4
    //   2428: goto -> 2431
    //   2431: aload_1
    //   2432: invokevirtual hasRemaining : ()Z
    //   2435: ifeq -> 174
    //   2438: aload_1
    //   2439: invokevirtual get : ()B
    //   2442: dup
    //   2443: bipush #102
    //   2445: if_icmpeq -> 2514
    //   2448: dup
    //   2449: bipush #116
    //   2451: if_icmpeq -> 2535
    //   2454: dup
    //   2455: bipush #58
    //   2457: if_icmpeq -> 2497
    //   2460: dup
    //   2461: bipush #13
    //   2463: if_icmpeq -> 2497
    //   2466: dup
    //   2467: bipush #10
    //   2469: if_icmpeq -> 2497
    //   2472: dup
    //   2473: bipush #32
    //   2475: if_icmpeq -> 2497
    //   2478: iconst_m1
    //   2479: istore #4
    //   2481: aload #7
    //   2483: ldc_w 'Re'
    //   2486: invokevirtual append : (Ljava/lang/String;)Ljava/lang/StringBuilder;
    //   2489: swap
    //   2490: invokevirtual append : (C)Ljava/lang/StringBuilder;
    //   2493: pop
    //   2494: goto -> 386
    //   2497: getstatic io/undertow/client/http/HttpResponseParser$$generated.HTTP_STRING_306 : Lio/undertow/util/HttpString;
    //   2500: aload_2
    //   2501: swap
    //   2502: putfield nextHeader : Lio/undertow/util/HttpString;
    //   2505: pop
    //   2506: aload_2
    //   2507: iconst_5
    //   2508: putfield state : I
    //   2511: goto -> 200
    //   2514: pop
    //   2515: bipush #-2
    //   2517: istore #4
    //   2519: getstatic io/undertow/client/http/HttpResponseParser$$generated.HTTP_STRING_308 : Lio/undertow/util/HttpString;
    //   2522: astore #6
    //   2524: getstatic io/undertow/client/http/HttpResponseParser$$generated.STATE_BYTES_307 : [B
    //   2527: astore #8
    //   2529: iconst_3
    //   2530: istore #5
    //   2532: goto -> 228
    //   2535: pop
    //   2536: bipush #-2
    //   2538: istore #4
    //   2540: getstatic io/undertow/client/http/HttpResponseParser$$generated.HTTP_STRING_318 : Lio/undertow/util/HttpString;
    //   2543: astore #6
    //   2545: getstatic io/undertow/client/http/HttpResponseParser$$generated.STATE_BYTES_317 : [B
    //   2548: astore #8
    //   2550: iconst_3
    //   2551: istore #5
    //   2553: goto -> 228
    //   2556: aload_1
    //   2557: invokevirtual hasRemaining : ()Z
    //   2560: ifeq -> 174
    //   2563: aload_1
    //   2564: invokevirtual get : ()B
    //   2567: dup
    //   2568: bipush #101
    //   2570: if_icmpeq -> 2660
    //   2573: dup
    //   2574: bipush #116
    //   2576: if_icmpeq -> 2639
    //   2579: dup
    //   2580: bipush #58
    //   2582: if_icmpeq -> 2622
    //   2585: dup
    //   2586: bipush #13
    //   2588: if_icmpeq -> 2622
    //   2591: dup
    //   2592: bipush #10
    //   2594: if_icmpeq -> 2622
    //   2597: dup
    //   2598: bipush #32
    //   2600: if_icmpeq -> 2622
    //   2603: iconst_m1
    //   2604: istore #4
    //   2606: aload #7
    //   2608: ldc_w 'S'
    //   2611: invokevirtual append : (Ljava/lang/String;)Ljava/lang/StringBuilder;
    //   2614: swap
    //   2615: invokevirtual append : (C)Ljava/lang/StringBuilder;
    //   2618: pop
    //   2619: goto -> 386
    //   2622: getstatic io/undertow/client/http/HttpResponseParser$$generated.HTTP_STRING_335 : Lio/undertow/util/HttpString;
    //   2625: aload_2
    //   2626: swap
    //   2627: putfield nextHeader : Lio/undertow/util/HttpString;
    //   2630: pop
    //   2631: aload_2
    //   2632: iconst_5
    //   2633: putfield state : I
    //   2636: goto -> 200
    //   2639: pop
    //   2640: bipush #-2
    //   2642: istore #4
    //   2644: getstatic io/undertow/client/http/HttpResponseParser$$generated.HTTP_STRING_364 : Lio/undertow/util/HttpString;
    //   2647: astore #6
    //   2649: getstatic io/undertow/client/http/HttpResponseParser$$generated.STATE_BYTES_363 : [B
    //   2652: astore #8
    //   2654: iconst_2
    //   2655: istore #5
    //   2657: goto -> 228
    //   2660: pop
    //   2661: bipush #18
    //   2663: istore #4
    //   2665: goto -> 2668
    //   2668: aload_1
    //   2669: invokevirtual hasRemaining : ()Z
    //   2672: ifeq -> 174
    //   2675: aload_1
    //   2676: invokevirtual get : ()B
    //   2679: dup
    //   2680: bipush #114
    //   2682: if_icmpeq -> 2751
    //   2685: dup
    //   2686: bipush #116
    //   2688: if_icmpeq -> 2772
    //   2691: dup
    //   2692: bipush #58
    //   2694: if_icmpeq -> 2734
    //   2697: dup
    //   2698: bipush #13
    //   2700: if_icmpeq -> 2734
    //   2703: dup
    //   2704: bipush #10
    //   2706: if_icmpeq -> 2734
    //   2709: dup
    //   2710: bipush #32
    //   2712: if_icmpeq -> 2734
    //   2715: iconst_m1
    //   2716: istore #4
    //   2718: aload #7
    //   2720: ldc_w 'Se'
    //   2723: invokevirtual append : (Ljava/lang/String;)Ljava/lang/StringBuilder;
    //   2726: swap
    //   2727: invokevirtual append : (C)Ljava/lang/StringBuilder;
    //   2730: pop
    //   2731: goto -> 386
    //   2734: getstatic io/undertow/client/http/HttpResponseParser$$generated.HTTP_STRING_336 : Lio/undertow/util/HttpString;
    //   2737: aload_2
    //   2738: swap
    //   2739: putfield nextHeader : Lio/undertow/util/HttpString;
    //   2742: pop
    //   2743: aload_2
    //   2744: iconst_5
    //   2745: putfield state : I
    //   2748: goto -> 200
    //   2751: pop
    //   2752: bipush #-2
    //   2754: istore #4
    //   2756: getstatic io/undertow/client/http/HttpResponseParser$$generated.HTTP_STRING_338 : Lio/undertow/util/HttpString;
    //   2759: astore #6
    //   2761: getstatic io/undertow/client/http/HttpResponseParser$$generated.STATE_BYTES_337 : [B
    //   2764: astore #8
    //   2766: iconst_3
    //   2767: istore #5
    //   2769: goto -> 228
    //   2772: pop
    //   2773: bipush #-2
    //   2775: istore #4
    //   2777: getstatic io/undertow/client/http/HttpResponseParser$$generated.HTTP_STRING_346 : Lio/undertow/util/HttpString;
    //   2780: astore #6
    //   2782: getstatic io/undertow/client/http/HttpResponseParser$$generated.STATE_BYTES_345 : [B
    //   2785: astore #8
    //   2787: iconst_3
    //   2788: istore #5
    //   2790: goto -> 228
    //   2793: aload_1
    //   2794: invokevirtual hasRemaining : ()Z
    //   2797: ifeq -> 174
    //   2800: aload_1
    //   2801: invokevirtual get : ()B
    //   2804: dup
    //   2805: bipush #114
    //   2807: if_icmpeq -> 2870
    //   2810: dup
    //   2811: bipush #58
    //   2813: if_icmpeq -> 2853
    //   2816: dup
    //   2817: bipush #13
    //   2819: if_icmpeq -> 2853
    //   2822: dup
    //   2823: bipush #10
    //   2825: if_icmpeq -> 2853
    //   2828: dup
    //   2829: bipush #32
    //   2831: if_icmpeq -> 2853
    //   2834: iconst_m1
    //   2835: istore #4
    //   2837: aload #7
    //   2839: ldc_w 'T'
    //   2842: invokevirtual append : (Ljava/lang/String;)Ljava/lang/StringBuilder;
    //   2845: swap
    //   2846: invokevirtual append : (C)Ljava/lang/StringBuilder;
    //   2849: pop
    //   2850: goto -> 386
    //   2853: getstatic io/undertow/client/http/HttpResponseParser$$generated.HTTP_STRING_411 : Lio/undertow/util/HttpString;
    //   2856: aload_2
    //   2857: swap
    //   2858: putfield nextHeader : Lio/undertow/util/HttpString;
    //   2861: pop
    //   2862: aload_2
    //   2863: iconst_5
    //   2864: putfield state : I
    //   2867: goto -> 200
    //   2870: pop
    //   2871: bipush #20
    //   2873: istore #4
    //   2875: goto -> 2878
    //   2878: aload_1
    //   2879: invokevirtual hasRemaining : ()Z
    //   2882: ifeq -> 174
    //   2885: aload_1
    //   2886: invokevirtual get : ()B
    //   2889: dup
    //   2890: bipush #97
    //   2892: if_icmpeq -> 2955
    //   2895: dup
    //   2896: bipush #58
    //   2898: if_icmpeq -> 2938
    //   2901: dup
    //   2902: bipush #13
    //   2904: if_icmpeq -> 2938
    //   2907: dup
    //   2908: bipush #10
    //   2910: if_icmpeq -> 2938
    //   2913: dup
    //   2914: bipush #32
    //   2916: if_icmpeq -> 2938
    //   2919: iconst_m1
    //   2920: istore #4
    //   2922: aload #7
    //   2924: ldc_w 'Tr'
    //   2927: invokevirtual append : (Ljava/lang/String;)Ljava/lang/StringBuilder;
    //   2930: swap
    //   2931: invokevirtual append : (C)Ljava/lang/StringBuilder;
    //   2934: pop
    //   2935: goto -> 386
    //   2938: getstatic io/undertow/client/http/HttpResponseParser$$generated.HTTP_STRING_412 : Lio/undertow/util/HttpString;
    //   2941: aload_2
    //   2942: swap
    //   2943: putfield nextHeader : Lio/undertow/util/HttpString;
    //   2946: pop
    //   2947: aload_2
    //   2948: iconst_5
    //   2949: putfield state : I
    //   2952: goto -> 200
    //   2955: pop
    //   2956: bipush #21
    //   2958: istore #4
    //   2960: goto -> 2963
    //   2963: aload_1
    //   2964: invokevirtual hasRemaining : ()Z
    //   2967: ifeq -> 174
    //   2970: aload_1
    //   2971: invokevirtual get : ()B
    //   2974: dup
    //   2975: bipush #105
    //   2977: if_icmpeq -> 3046
    //   2980: dup
    //   2981: bipush #110
    //   2983: if_icmpeq -> 3067
    //   2986: dup
    //   2987: bipush #58
    //   2989: if_icmpeq -> 3029
    //   2992: dup
    //   2993: bipush #13
    //   2995: if_icmpeq -> 3029
    //   2998: dup
    //   2999: bipush #10
    //   3001: if_icmpeq -> 3029
    //   3004: dup
    //   3005: bipush #32
    //   3007: if_icmpeq -> 3029
    //   3010: iconst_m1
    //   3011: istore #4
    //   3013: aload #7
    //   3015: ldc_w 'Tra'
    //   3018: invokevirtual append : (Ljava/lang/String;)Ljava/lang/StringBuilder;
    //   3021: swap
    //   3022: invokevirtual append : (C)Ljava/lang/StringBuilder;
    //   3025: pop
    //   3026: goto -> 386
    //   3029: getstatic io/undertow/client/http/HttpResponseParser$$generated.HTTP_STRING_413 : Lio/undertow/util/HttpString;
    //   3032: aload_2
    //   3033: swap
    //   3034: putfield nextHeader : Lio/undertow/util/HttpString;
    //   3037: pop
    //   3038: aload_2
    //   3039: iconst_5
    //   3040: putfield state : I
    //   3043: goto -> 200
    //   3046: pop
    //   3047: bipush #-2
    //   3049: istore #4
    //   3051: getstatic io/undertow/client/http/HttpResponseParser$$generated.HTTP_STRING_415 : Lio/undertow/util/HttpString;
    //   3054: astore #6
    //   3056: getstatic io/undertow/client/http/HttpResponseParser$$generated.STATE_BYTES_414 : [B
    //   3059: astore #8
    //   3061: iconst_4
    //   3062: istore #5
    //   3064: goto -> 228
    //   3067: pop
    //   3068: bipush #-2
    //   3070: istore #4
    //   3072: getstatic io/undertow/client/http/HttpResponseParser$$generated.HTTP_STRING_423 : Lio/undertow/util/HttpString;
    //   3075: astore #6
    //   3077: getstatic io/undertow/client/http/HttpResponseParser$$generated.STATE_BYTES_422 : [B
    //   3080: astore #8
    //   3082: iconst_4
    //   3083: istore #5
    //   3085: goto -> 228
    //   3088: aload_1
    //   3089: invokevirtual hasRemaining : ()Z
    //   3092: ifeq -> 174
    //   3095: aload_1
    //   3096: invokevirtual get : ()B
    //   3099: dup
    //   3100: bipush #97
    //   3102: if_icmpeq -> 3171
    //   3105: dup
    //   3106: bipush #105
    //   3108: if_icmpeq -> 3192
    //   3111: dup
    //   3112: bipush #58
    //   3114: if_icmpeq -> 3154
    //   3117: dup
    //   3118: bipush #13
    //   3120: if_icmpeq -> 3154
    //   3123: dup
    //   3124: bipush #10
    //   3126: if_icmpeq -> 3154
    //   3129: dup
    //   3130: bipush #32
    //   3132: if_icmpeq -> 3154
    //   3135: iconst_m1
    //   3136: istore #4
    //   3138: aload #7
    //   3140: ldc_w 'V'
    //   3143: invokevirtual append : (Ljava/lang/String;)Ljava/lang/StringBuilder;
    //   3146: swap
    //   3147: invokevirtual append : (C)Ljava/lang/StringBuilder;
    //   3150: pop
    //   3151: goto -> 386
    //   3154: getstatic io/undertow/client/http/HttpResponseParser$$generated.HTTP_STRING_450 : Lio/undertow/util/HttpString;
    //   3157: aload_2
    //   3158: swap
    //   3159: putfield nextHeader : Lio/undertow/util/HttpString;
    //   3162: pop
    //   3163: aload_2
    //   3164: iconst_5
    //   3165: putfield state : I
    //   3168: goto -> 200
    //   3171: pop
    //   3172: bipush #-2
    //   3174: istore #4
    //   3176: getstatic io/undertow/client/http/HttpResponseParser$$generated.HTTP_STRING_452 : Lio/undertow/util/HttpString;
    //   3179: astore #6
    //   3181: getstatic io/undertow/client/http/HttpResponseParser$$generated.STATE_BYTES_451 : [B
    //   3184: astore #8
    //   3186: iconst_2
    //   3187: istore #5
    //   3189: goto -> 228
    //   3192: pop
    //   3193: bipush #-2
    //   3195: istore #4
    //   3197: getstatic io/undertow/client/http/HttpResponseParser$$generated.HTTP_STRING_458 : Lio/undertow/util/HttpString;
    //   3200: astore #6
    //   3202: getstatic io/undertow/client/http/HttpResponseParser$$generated.STATE_BYTES_457 : [B
    //   3205: astore #8
    //   3207: iconst_2
    //   3208: istore #5
    //   3210: goto -> 228
    //   3213: aload_1
    //   3214: invokevirtual hasRemaining : ()Z
    //   3217: ifeq -> 174
    //   3220: aload_1
    //   3221: invokevirtual get : ()B
    //   3224: dup
    //   3225: bipush #97
    //   3227: if_icmpeq -> 3317
    //   3230: dup
    //   3231: bipush #87
    //   3233: if_icmpeq -> 3296
    //   3236: dup
    //   3237: bipush #58
    //   3239: if_icmpeq -> 3279
    //   3242: dup
    //   3243: bipush #13
    //   3245: if_icmpeq -> 3279
    //   3248: dup
    //   3249: bipush #10
    //   3251: if_icmpeq -> 3279
    //   3254: dup
    //   3255: bipush #32
    //   3257: if_icmpeq -> 3279
    //   3260: iconst_m1
    //   3261: istore #4
    //   3263: aload #7
    //   3265: ldc_w 'W'
    //   3268: invokevirtual append : (Ljava/lang/String;)Ljava/lang/StringBuilder;
    //   3271: swap
    //   3272: invokevirtual append : (C)Ljava/lang/StringBuilder;
    //   3275: pop
    //   3276: goto -> 386
    //   3279: getstatic io/undertow/client/http/HttpResponseParser$$generated.HTTP_STRING_461 : Lio/undertow/util/HttpString;
    //   3282: aload_2
    //   3283: swap
    //   3284: putfield nextHeader : Lio/undertow/util/HttpString;
    //   3287: pop
    //   3288: aload_2
    //   3289: iconst_5
    //   3290: putfield state : I
    //   3293: goto -> 200
    //   3296: pop
    //   3297: bipush #-2
    //   3299: istore #4
    //   3301: getstatic io/undertow/client/http/HttpResponseParser$$generated.HTTP_STRING_475 : Lio/undertow/util/HttpString;
    //   3304: astore #6
    //   3306: getstatic io/undertow/client/http/HttpResponseParser$$generated.STATE_BYTES_474 : [B
    //   3309: astore #8
    //   3311: iconst_2
    //   3312: istore #5
    //   3314: goto -> 228
    //   3317: pop
    //   3318: bipush #-2
    //   3320: istore #4
    //   3322: getstatic io/undertow/client/http/HttpResponseParser$$generated.HTTP_STRING_463 : Lio/undertow/util/HttpString;
    //   3325: astore #6
    //   3327: getstatic io/undertow/client/http/HttpResponseParser$$generated.STATE_BYTES_462 : [B
    //   3330: astore #8
    //   3332: iconst_2
    //   3333: istore #5
    //   3335: goto -> 228
  }
  
  static {
    if (map.get("HTTP/0.9") != null) {
      HTTP_STRING_9 = map.get("HTTP/0.9");
    } else {
      map.get("HTTP/0.9");
      HTTP_STRING_9 = new HttpString("HTTP/0.9");
    } 
    STATE_BYTES_10 = "HTTP/0.9".getBytes("ISO-8859-1");
    if (map.get("HTTP/0.9") != null) {
      HTTP_STRING_11 = map.get("HTTP/0.9");
    } else {
      map.get("HTTP/0.9");
      HTTP_STRING_11 = new HttpString("HTTP/0.9");
    } 
    STATE_BYTES_12 = "HTTP/0.9".getBytes("ISO-8859-1");
    if (map.get("HTTP/0.9") != null) {
      HTTP_STRING_13 = map.get("HTTP/0.9");
    } else {
      map.get("HTTP/0.9");
      HTTP_STRING_13 = new HttpString("HTTP/0.9");
    } 
    if (map.get("HTTP/1") != null) {
      HTTP_STRING_14 = map.get("HTTP/1");
    } else {
      map.get("HTTP/1");
      HTTP_STRING_14 = new HttpString("HTTP/1");
    } 
    if (map.get("HTTP/1.") != null) {
      HTTP_STRING_15 = map.get("HTTP/1.");
    } else {
      map.get("HTTP/1.");
      HTTP_STRING_15 = new HttpString("HTTP/1.");
    } 
    STATE_BYTES_16 = "HTTP/1.0".getBytes("ISO-8859-1");
    if (map.get("HTTP/1.0") != null) {
      HTTP_STRING_17 = map.get("HTTP/1.0");
    } else {
      map.get("HTTP/1.0");
      HTTP_STRING_17 = new HttpString("HTTP/1.0");
    } 
    STATE_BYTES_18 = "HTTP/1.1".getBytes("ISO-8859-1");
    if (map.get("HTTP/1.1") != null) {
      HTTP_STRING_19 = map.get("HTTP/1.1");
    } else {
      map.get("HTTP/1.1");
      HTTP_STRING_19 = new HttpString("HTTP/1.1");
    } 
    if (map.get("A") != null) {
      HTTP_STRING_21 = map.get("A");
    } else {
      map.get("A");
      HTTP_STRING_21 = new HttpString("A");
    } 
    STATE_BYTES_22 = "Accept-Ranges".getBytes("ISO-8859-1");
    if (map.get("Accept-Ranges") != null) {
      HTTP_STRING_23 = map.get("Accept-Ranges");
    } else {
      map.get("Accept-Ranges");
      HTTP_STRING_23 = new HttpString("Accept-Ranges");
    } 
    STATE_BYTES_24 = "Accept-Ranges".getBytes("ISO-8859-1");
    if (map.get("Accept-Ranges") != null) {
      HTTP_STRING_25 = map.get("Accept-Ranges");
    } else {
      map.get("Accept-Ranges");
      HTTP_STRING_25 = new HttpString("Accept-Ranges");
    } 
    STATE_BYTES_26 = "Accept-Ranges".getBytes("ISO-8859-1");
    if (map.get("Accept-Ranges") != null) {
      HTTP_STRING_27 = map.get("Accept-Ranges");
    } else {
      map.get("Accept-Ranges");
      HTTP_STRING_27 = new HttpString("Accept-Ranges");
    } 
    STATE_BYTES_28 = "Accept-Ranges".getBytes("ISO-8859-1");
    if (map.get("Accept-Ranges") != null) {
      HTTP_STRING_29 = map.get("Accept-Ranges");
    } else {
      map.get("Accept-Ranges");
      HTTP_STRING_29 = new HttpString("Accept-Ranges");
    } 
    STATE_BYTES_30 = "Accept-Ranges".getBytes("ISO-8859-1");
    if (map.get("Accept-Ranges") != null) {
      HTTP_STRING_31 = map.get("Accept-Ranges");
    } else {
      map.get("Accept-Ranges");
      HTTP_STRING_31 = new HttpString("Accept-Ranges");
    } 
    STATE_BYTES_32 = "Accept-Ranges".getBytes("ISO-8859-1");
    if (map.get("Accept-Ranges") != null) {
      HTTP_STRING_33 = map.get("Accept-Ranges");
    } else {
      map.get("Accept-Ranges");
      HTTP_STRING_33 = new HttpString("Accept-Ranges");
    } 
    STATE_BYTES_34 = "Accept-Ranges".getBytes("ISO-8859-1");
    if (map.get("Accept-Ranges") != null) {
      HTTP_STRING_35 = map.get("Accept-Ranges");
    } else {
      map.get("Accept-Ranges");
      HTTP_STRING_35 = new HttpString("Accept-Ranges");
    } 
    STATE_BYTES_36 = "Accept-Ranges".getBytes("ISO-8859-1");
    if (map.get("Accept-Ranges") != null) {
      HTTP_STRING_37 = map.get("Accept-Ranges");
    } else {
      map.get("Accept-Ranges");
      HTTP_STRING_37 = new HttpString("Accept-Ranges");
    } 
    STATE_BYTES_38 = "Accept-Ranges".getBytes("ISO-8859-1");
    if (map.get("Accept-Ranges") != null) {
      HTTP_STRING_39 = map.get("Accept-Ranges");
    } else {
      map.get("Accept-Ranges");
      HTTP_STRING_39 = new HttpString("Accept-Ranges");
    } 
    STATE_BYTES_40 = "Accept-Ranges".getBytes("ISO-8859-1");
    if (map.get("Accept-Ranges") != null) {
      HTTP_STRING_41 = map.get("Accept-Ranges");
    } else {
      map.get("Accept-Ranges");
      HTTP_STRING_41 = new HttpString("Accept-Ranges");
    } 
    STATE_BYTES_42 = "Accept-Ranges".getBytes("ISO-8859-1");
    if (map.get("Accept-Ranges") != null) {
      HTTP_STRING_43 = map.get("Accept-Ranges");
    } else {
      map.get("Accept-Ranges");
      HTTP_STRING_43 = new HttpString("Accept-Ranges");
    } 
    STATE_BYTES_44 = "Accept-Ranges".getBytes("ISO-8859-1");
    if (map.get("Accept-Ranges") != null) {
      HTTP_STRING_45 = map.get("Accept-Ranges");
    } else {
      map.get("Accept-Ranges");
      HTTP_STRING_45 = new HttpString("Accept-Ranges");
    } 
    STATE_BYTES_46 = "Age".getBytes("ISO-8859-1");
    if (map.get("Age") != null) {
      HTTP_STRING_47 = map.get("Age");
    } else {
      map.get("Age");
      HTTP_STRING_47 = new HttpString("Age");
    } 
    STATE_BYTES_48 = "Age".getBytes("ISO-8859-1");
    if (map.get("Age") != null) {
      HTTP_STRING_49 = map.get("Age");
    } else {
      map.get("Age");
      HTTP_STRING_49 = new HttpString("Age");
    } 
    if (map.get("C") != null) {
      HTTP_STRING_50 = map.get("C");
    } else {
      map.get("C");
      HTTP_STRING_50 = new HttpString("C");
    } 
    STATE_BYTES_51 = "Cache-Control".getBytes("ISO-8859-1");
    if (map.get("Cache-Control") != null) {
      HTTP_STRING_52 = map.get("Cache-Control");
    } else {
      map.get("Cache-Control");
      HTTP_STRING_52 = new HttpString("Cache-Control");
    } 
    STATE_BYTES_53 = "Cache-Control".getBytes("ISO-8859-1");
    if (map.get("Cache-Control") != null) {
      HTTP_STRING_54 = map.get("Cache-Control");
    } else {
      map.get("Cache-Control");
      HTTP_STRING_54 = new HttpString("Cache-Control");
    } 
    STATE_BYTES_55 = "Cache-Control".getBytes("ISO-8859-1");
    if (map.get("Cache-Control") != null) {
      HTTP_STRING_56 = map.get("Cache-Control");
    } else {
      map.get("Cache-Control");
      HTTP_STRING_56 = new HttpString("Cache-Control");
    } 
    STATE_BYTES_57 = "Cache-Control".getBytes("ISO-8859-1");
    if (map.get("Cache-Control") != null) {
      HTTP_STRING_58 = map.get("Cache-Control");
    } else {
      map.get("Cache-Control");
      HTTP_STRING_58 = new HttpString("Cache-Control");
    } 
    STATE_BYTES_59 = "Cache-Control".getBytes("ISO-8859-1");
    if (map.get("Cache-Control") != null) {
      HTTP_STRING_60 = map.get("Cache-Control");
    } else {
      map.get("Cache-Control");
      HTTP_STRING_60 = new HttpString("Cache-Control");
    } 
    STATE_BYTES_61 = "Cache-Control".getBytes("ISO-8859-1");
    if (map.get("Cache-Control") != null) {
      HTTP_STRING_62 = map.get("Cache-Control");
    } else {
      map.get("Cache-Control");
      HTTP_STRING_62 = new HttpString("Cache-Control");
    } 
    STATE_BYTES_63 = "Cache-Control".getBytes("ISO-8859-1");
    if (map.get("Cache-Control") != null) {
      HTTP_STRING_64 = map.get("Cache-Control");
    } else {
      map.get("Cache-Control");
      HTTP_STRING_64 = new HttpString("Cache-Control");
    } 
    STATE_BYTES_65 = "Cache-Control".getBytes("ISO-8859-1");
    if (map.get("Cache-Control") != null) {
      HTTP_STRING_66 = map.get("Cache-Control");
    } else {
      map.get("Cache-Control");
      HTTP_STRING_66 = new HttpString("Cache-Control");
    } 
    STATE_BYTES_67 = "Cache-Control".getBytes("ISO-8859-1");
    if (map.get("Cache-Control") != null) {
      HTTP_STRING_68 = map.get("Cache-Control");
    } else {
      map.get("Cache-Control");
      HTTP_STRING_68 = new HttpString("Cache-Control");
    } 
    STATE_BYTES_69 = "Cache-Control".getBytes("ISO-8859-1");
    if (map.get("Cache-Control") != null) {
      HTTP_STRING_70 = map.get("Cache-Control");
    } else {
      map.get("Cache-Control");
      HTTP_STRING_70 = new HttpString("Cache-Control");
    } 
    STATE_BYTES_71 = "Cache-Control".getBytes("ISO-8859-1");
    if (map.get("Cache-Control") != null) {
      HTTP_STRING_72 = map.get("Cache-Control");
    } else {
      map.get("Cache-Control");
      HTTP_STRING_72 = new HttpString("Cache-Control");
    } 
    STATE_BYTES_73 = "Cache-Control".getBytes("ISO-8859-1");
    if (map.get("Cache-Control") != null) {
      HTTP_STRING_74 = map.get("Cache-Control");
    } else {
      map.get("Cache-Control");
      HTTP_STRING_74 = new HttpString("Cache-Control");
    } 
    if (map.get("Co") != null) {
      HTTP_STRING_75 = map.get("Co");
    } else {
      map.get("Co");
      HTTP_STRING_75 = new HttpString("Co");
    } 
    if (map.get("Con") != null) {
      HTTP_STRING_76 = map.get("Con");
    } else {
      map.get("Con");
      HTTP_STRING_76 = new HttpString("Con");
    } 
    STATE_BYTES_77 = "Connection".getBytes("ISO-8859-1");
    if (map.get("Connection") != null) {
      HTTP_STRING_78 = map.get("Connection");
    } else {
      map.get("Connection");
      HTTP_STRING_78 = new HttpString("Connection");
    } 
    STATE_BYTES_79 = "Connection".getBytes("ISO-8859-1");
    if (map.get("Connection") != null) {
      HTTP_STRING_80 = map.get("Connection");
    } else {
      map.get("Connection");
      HTTP_STRING_80 = new HttpString("Connection");
    } 
    STATE_BYTES_81 = "Connection".getBytes("ISO-8859-1");
    if (map.get("Connection") != null) {
      HTTP_STRING_82 = map.get("Connection");
    } else {
      map.get("Connection");
      HTTP_STRING_82 = new HttpString("Connection");
    } 
    STATE_BYTES_83 = "Connection".getBytes("ISO-8859-1");
    if (map.get("Connection") != null) {
      HTTP_STRING_84 = map.get("Connection");
    } else {
      map.get("Connection");
      HTTP_STRING_84 = new HttpString("Connection");
    } 
    STATE_BYTES_85 = "Connection".getBytes("ISO-8859-1");
    if (map.get("Connection") != null) {
      HTTP_STRING_86 = map.get("Connection");
    } else {
      map.get("Connection");
      HTTP_STRING_86 = new HttpString("Connection");
    } 
    STATE_BYTES_87 = "Connection".getBytes("ISO-8859-1");
    if (map.get("Connection") != null) {
      HTTP_STRING_88 = map.get("Connection");
    } else {
      map.get("Connection");
      HTTP_STRING_88 = new HttpString("Connection");
    } 
    STATE_BYTES_89 = "Connection".getBytes("ISO-8859-1");
    if (map.get("Connection") != null) {
      HTTP_STRING_90 = map.get("Connection");
    } else {
      map.get("Connection");
      HTTP_STRING_90 = new HttpString("Connection");
    } 
    if (map.get("Cont") != null) {
      HTTP_STRING_91 = map.get("Cont");
    } else {
      map.get("Cont");
      HTTP_STRING_91 = new HttpString("Cont");
    } 
    if (map.get("Conte") != null) {
      HTTP_STRING_92 = map.get("Conte");
    } else {
      map.get("Conte");
      HTTP_STRING_92 = new HttpString("Conte");
    } 
    if (map.get("Conten") != null) {
      HTTP_STRING_93 = map.get("Conten");
    } else {
      map.get("Conten");
      HTTP_STRING_93 = new HttpString("Conten");
    } 
    if (map.get("Content") != null) {
      HTTP_STRING_94 = map.get("Content");
    } else {
      map.get("Content");
      HTTP_STRING_94 = new HttpString("Content");
    } 
    if (map.get("Content-") != null) {
      HTTP_STRING_95 = map.get("Content-");
    } else {
      map.get("Content-");
      HTTP_STRING_95 = new HttpString("Content-");
    } 
    STATE_BYTES_96 = "Content-Disposition".getBytes("ISO-8859-1");
    if (map.get("Content-Disposition") != null) {
      HTTP_STRING_97 = map.get("Content-Disposition");
    } else {
      map.get("Content-Disposition");
      HTTP_STRING_97 = new HttpString("Content-Disposition");
    } 
    STATE_BYTES_98 = "Content-Disposition".getBytes("ISO-8859-1");
    if (map.get("Content-Disposition") != null) {
      HTTP_STRING_99 = map.get("Content-Disposition");
    } else {
      map.get("Content-Disposition");
      HTTP_STRING_99 = new HttpString("Content-Disposition");
    } 
    STATE_BYTES_100 = "Content-Disposition".getBytes("ISO-8859-1");
    if (map.get("Content-Disposition") != null) {
      HTTP_STRING_101 = map.get("Content-Disposition");
    } else {
      map.get("Content-Disposition");
      HTTP_STRING_101 = new HttpString("Content-Disposition");
    } 
    STATE_BYTES_102 = "Content-Disposition".getBytes("ISO-8859-1");
    if (map.get("Content-Disposition") != null) {
      HTTP_STRING_103 = map.get("Content-Disposition");
    } else {
      map.get("Content-Disposition");
      HTTP_STRING_103 = new HttpString("Content-Disposition");
    } 
    STATE_BYTES_104 = "Content-Disposition".getBytes("ISO-8859-1");
    if (map.get("Content-Disposition") != null) {
      HTTP_STRING_105 = map.get("Content-Disposition");
    } else {
      map.get("Content-Disposition");
      HTTP_STRING_105 = new HttpString("Content-Disposition");
    } 
    STATE_BYTES_106 = "Content-Disposition".getBytes("ISO-8859-1");
    if (map.get("Content-Disposition") != null) {
      HTTP_STRING_107 = map.get("Content-Disposition");
    } else {
      map.get("Content-Disposition");
      HTTP_STRING_107 = new HttpString("Content-Disposition");
    } 
    STATE_BYTES_108 = "Content-Disposition".getBytes("ISO-8859-1");
    if (map.get("Content-Disposition") != null) {
      HTTP_STRING_109 = map.get("Content-Disposition");
    } else {
      map.get("Content-Disposition");
      HTTP_STRING_109 = new HttpString("Content-Disposition");
    } 
    STATE_BYTES_110 = "Content-Disposition".getBytes("ISO-8859-1");
    if (map.get("Content-Disposition") != null) {
      HTTP_STRING_111 = map.get("Content-Disposition");
    } else {
      map.get("Content-Disposition");
      HTTP_STRING_111 = new HttpString("Content-Disposition");
    } 
    STATE_BYTES_112 = "Content-Disposition".getBytes("ISO-8859-1");
    if (map.get("Content-Disposition") != null) {
      HTTP_STRING_113 = map.get("Content-Disposition");
    } else {
      map.get("Content-Disposition");
      HTTP_STRING_113 = new HttpString("Content-Disposition");
    } 
    STATE_BYTES_114 = "Content-Disposition".getBytes("ISO-8859-1");
    if (map.get("Content-Disposition") != null) {
      HTTP_STRING_115 = map.get("Content-Disposition");
    } else {
      map.get("Content-Disposition");
      HTTP_STRING_115 = new HttpString("Content-Disposition");
    } 
    STATE_BYTES_116 = "Content-Disposition".getBytes("ISO-8859-1");
    if (map.get("Content-Disposition") != null) {
      HTTP_STRING_117 = map.get("Content-Disposition");
    } else {
      map.get("Content-Disposition");
      HTTP_STRING_117 = new HttpString("Content-Disposition");
    } 
    STATE_BYTES_118 = "Content-Encoding".getBytes("ISO-8859-1");
    if (map.get("Content-Encoding") != null) {
      HTTP_STRING_119 = map.get("Content-Encoding");
    } else {
      map.get("Content-Encoding");
      HTTP_STRING_119 = new HttpString("Content-Encoding");
    } 
    STATE_BYTES_120 = "Content-Encoding".getBytes("ISO-8859-1");
    if (map.get("Content-Encoding") != null) {
      HTTP_STRING_121 = map.get("Content-Encoding");
    } else {
      map.get("Content-Encoding");
      HTTP_STRING_121 = new HttpString("Content-Encoding");
    } 
    STATE_BYTES_122 = "Content-Encoding".getBytes("ISO-8859-1");
    if (map.get("Content-Encoding") != null) {
      HTTP_STRING_123 = map.get("Content-Encoding");
    } else {
      map.get("Content-Encoding");
      HTTP_STRING_123 = new HttpString("Content-Encoding");
    } 
    STATE_BYTES_124 = "Content-Encoding".getBytes("ISO-8859-1");
    if (map.get("Content-Encoding") != null) {
      HTTP_STRING_125 = map.get("Content-Encoding");
    } else {
      map.get("Content-Encoding");
      HTTP_STRING_125 = new HttpString("Content-Encoding");
    } 
    STATE_BYTES_126 = "Content-Encoding".getBytes("ISO-8859-1");
    if (map.get("Content-Encoding") != null) {
      HTTP_STRING_127 = map.get("Content-Encoding");
    } else {
      map.get("Content-Encoding");
      HTTP_STRING_127 = new HttpString("Content-Encoding");
    } 
    STATE_BYTES_128 = "Content-Encoding".getBytes("ISO-8859-1");
    if (map.get("Content-Encoding") != null) {
      HTTP_STRING_129 = map.get("Content-Encoding");
    } else {
      map.get("Content-Encoding");
      HTTP_STRING_129 = new HttpString("Content-Encoding");
    } 
    STATE_BYTES_130 = "Content-Encoding".getBytes("ISO-8859-1");
    if (map.get("Content-Encoding") != null) {
      HTTP_STRING_131 = map.get("Content-Encoding");
    } else {
      map.get("Content-Encoding");
      HTTP_STRING_131 = new HttpString("Content-Encoding");
    } 
    STATE_BYTES_132 = "Content-Encoding".getBytes("ISO-8859-1");
    if (map.get("Content-Encoding") != null) {
      HTTP_STRING_133 = map.get("Content-Encoding");
    } else {
      map.get("Content-Encoding");
      HTTP_STRING_133 = new HttpString("Content-Encoding");
    } 
    if (map.get("Content-L") != null) {
      HTTP_STRING_134 = map.get("Content-L");
    } else {
      map.get("Content-L");
      HTTP_STRING_134 = new HttpString("Content-L");
    } 
    STATE_BYTES_135 = "Content-Language".getBytes("ISO-8859-1");
    if (map.get("Content-Language") != null) {
      HTTP_STRING_136 = map.get("Content-Language");
    } else {
      map.get("Content-Language");
      HTTP_STRING_136 = new HttpString("Content-Language");
    } 
    STATE_BYTES_137 = "Content-Language".getBytes("ISO-8859-1");
    if (map.get("Content-Language") != null) {
      HTTP_STRING_138 = map.get("Content-Language");
    } else {
      map.get("Content-Language");
      HTTP_STRING_138 = new HttpString("Content-Language");
    } 
    STATE_BYTES_139 = "Content-Language".getBytes("ISO-8859-1");
    if (map.get("Content-Language") != null) {
      HTTP_STRING_140 = map.get("Content-Language");
    } else {
      map.get("Content-Language");
      HTTP_STRING_140 = new HttpString("Content-Language");
    } 
    STATE_BYTES_141 = "Content-Language".getBytes("ISO-8859-1");
    if (map.get("Content-Language") != null) {
      HTTP_STRING_142 = map.get("Content-Language");
    } else {
      map.get("Content-Language");
      HTTP_STRING_142 = new HttpString("Content-Language");
    } 
    STATE_BYTES_143 = "Content-Language".getBytes("ISO-8859-1");
    if (map.get("Content-Language") != null) {
      HTTP_STRING_144 = map.get("Content-Language");
    } else {
      map.get("Content-Language");
      HTTP_STRING_144 = new HttpString("Content-Language");
    } 
    STATE_BYTES_145 = "Content-Language".getBytes("ISO-8859-1");
    if (map.get("Content-Language") != null) {
      HTTP_STRING_146 = map.get("Content-Language");
    } else {
      map.get("Content-Language");
      HTTP_STRING_146 = new HttpString("Content-Language");
    } 
    STATE_BYTES_147 = "Content-Language".getBytes("ISO-8859-1");
    if (map.get("Content-Language") != null) {
      HTTP_STRING_148 = map.get("Content-Language");
    } else {
      map.get("Content-Language");
      HTTP_STRING_148 = new HttpString("Content-Language");
    } 
    STATE_BYTES_149 = "Content-Length".getBytes("ISO-8859-1");
    if (map.get("Content-Length") != null) {
      HTTP_STRING_150 = map.get("Content-Length");
    } else {
      map.get("Content-Length");
      HTTP_STRING_150 = new HttpString("Content-Length");
    } 
    STATE_BYTES_151 = "Content-Length".getBytes("ISO-8859-1");
    if (map.get("Content-Length") != null) {
      HTTP_STRING_152 = map.get("Content-Length");
    } else {
      map.get("Content-Length");
      HTTP_STRING_152 = new HttpString("Content-Length");
    } 
    STATE_BYTES_153 = "Content-Length".getBytes("ISO-8859-1");
    if (map.get("Content-Length") != null) {
      HTTP_STRING_154 = map.get("Content-Length");
    } else {
      map.get("Content-Length");
      HTTP_STRING_154 = new HttpString("Content-Length");
    } 
    STATE_BYTES_155 = "Content-Length".getBytes("ISO-8859-1");
    if (map.get("Content-Length") != null) {
      HTTP_STRING_156 = map.get("Content-Length");
    } else {
      map.get("Content-Length");
      HTTP_STRING_156 = new HttpString("Content-Length");
    } 
    STATE_BYTES_157 = "Content-Length".getBytes("ISO-8859-1");
    if (map.get("Content-Length") != null) {
      HTTP_STRING_158 = map.get("Content-Length");
    } else {
      map.get("Content-Length");
      HTTP_STRING_158 = new HttpString("Content-Length");
    } 
    STATE_BYTES_159 = "Content-Location".getBytes("ISO-8859-1");
    if (map.get("Content-Location") != null) {
      HTTP_STRING_160 = map.get("Content-Location");
    } else {
      map.get("Content-Location");
      HTTP_STRING_160 = new HttpString("Content-Location");
    } 
    STATE_BYTES_161 = "Content-Location".getBytes("ISO-8859-1");
    if (map.get("Content-Location") != null) {
      HTTP_STRING_162 = map.get("Content-Location");
    } else {
      map.get("Content-Location");
      HTTP_STRING_162 = new HttpString("Content-Location");
    } 
    STATE_BYTES_163 = "Content-Location".getBytes("ISO-8859-1");
    if (map.get("Content-Location") != null) {
      HTTP_STRING_164 = map.get("Content-Location");
    } else {
      map.get("Content-Location");
      HTTP_STRING_164 = new HttpString("Content-Location");
    } 
    STATE_BYTES_165 = "Content-Location".getBytes("ISO-8859-1");
    if (map.get("Content-Location") != null) {
      HTTP_STRING_166 = map.get("Content-Location");
    } else {
      map.get("Content-Location");
      HTTP_STRING_166 = new HttpString("Content-Location");
    } 
    STATE_BYTES_167 = "Content-Location".getBytes("ISO-8859-1");
    if (map.get("Content-Location") != null) {
      HTTP_STRING_168 = map.get("Content-Location");
    } else {
      map.get("Content-Location");
      HTTP_STRING_168 = new HttpString("Content-Location");
    } 
    STATE_BYTES_169 = "Content-Location".getBytes("ISO-8859-1");
    if (map.get("Content-Location") != null) {
      HTTP_STRING_170 = map.get("Content-Location");
    } else {
      map.get("Content-Location");
      HTTP_STRING_170 = new HttpString("Content-Location");
    } 
    STATE_BYTES_171 = "Content-Location".getBytes("ISO-8859-1");
    if (map.get("Content-Location") != null) {
      HTTP_STRING_172 = map.get("Content-Location");
    } else {
      map.get("Content-Location");
      HTTP_STRING_172 = new HttpString("Content-Location");
    } 
    STATE_BYTES_173 = "Content-MD5".getBytes("ISO-8859-1");
    if (map.get("Content-MD5") != null) {
      HTTP_STRING_174 = map.get("Content-MD5");
    } else {
      map.get("Content-MD5");
      HTTP_STRING_174 = new HttpString("Content-MD5");
    } 
    STATE_BYTES_175 = "Content-MD5".getBytes("ISO-8859-1");
    if (map.get("Content-MD5") != null) {
      HTTP_STRING_176 = map.get("Content-MD5");
    } else {
      map.get("Content-MD5");
      HTTP_STRING_176 = new HttpString("Content-MD5");
    } 
    STATE_BYTES_177 = "Content-MD5".getBytes("ISO-8859-1");
    if (map.get("Content-MD5") != null) {
      HTTP_STRING_178 = map.get("Content-MD5");
    } else {
      map.get("Content-MD5");
      HTTP_STRING_178 = new HttpString("Content-MD5");
    } 
    STATE_BYTES_179 = "Content-Range".getBytes("ISO-8859-1");
    if (map.get("Content-Range") != null) {
      HTTP_STRING_180 = map.get("Content-Range");
    } else {
      map.get("Content-Range");
      HTTP_STRING_180 = new HttpString("Content-Range");
    } 
    STATE_BYTES_181 = "Content-Range".getBytes("ISO-8859-1");
    if (map.get("Content-Range") != null) {
      HTTP_STRING_182 = map.get("Content-Range");
    } else {
      map.get("Content-Range");
      HTTP_STRING_182 = new HttpString("Content-Range");
    } 
    STATE_BYTES_183 = "Content-Range".getBytes("ISO-8859-1");
    if (map.get("Content-Range") != null) {
      HTTP_STRING_184 = map.get("Content-Range");
    } else {
      map.get("Content-Range");
      HTTP_STRING_184 = new HttpString("Content-Range");
    } 
    STATE_BYTES_185 = "Content-Range".getBytes("ISO-8859-1");
    if (map.get("Content-Range") != null) {
      HTTP_STRING_186 = map.get("Content-Range");
    } else {
      map.get("Content-Range");
      HTTP_STRING_186 = new HttpString("Content-Range");
    } 
    STATE_BYTES_187 = "Content-Range".getBytes("ISO-8859-1");
    if (map.get("Content-Range") != null) {
      HTTP_STRING_188 = map.get("Content-Range");
    } else {
      map.get("Content-Range");
      HTTP_STRING_188 = new HttpString("Content-Range");
    } 
    STATE_BYTES_189 = "Content-Type".getBytes("ISO-8859-1");
    if (map.get("Content-Type") != null) {
      HTTP_STRING_190 = map.get("Content-Type");
    } else {
      map.get("Content-Type");
      HTTP_STRING_190 = new HttpString("Content-Type");
    } 
    STATE_BYTES_191 = "Content-Type".getBytes("ISO-8859-1");
    if (map.get("Content-Type") != null) {
      HTTP_STRING_192 = map.get("Content-Type");
    } else {
      map.get("Content-Type");
      HTTP_STRING_192 = new HttpString("Content-Type");
    } 
    STATE_BYTES_193 = "Content-Type".getBytes("ISO-8859-1");
    if (map.get("Content-Type") != null) {
      HTTP_STRING_194 = map.get("Content-Type");
    } else {
      map.get("Content-Type");
      HTTP_STRING_194 = new HttpString("Content-Type");
    } 
    STATE_BYTES_195 = "Content-Type".getBytes("ISO-8859-1");
    if (map.get("Content-Type") != null) {
      HTTP_STRING_196 = map.get("Content-Type");
    } else {
      map.get("Content-Type");
      HTTP_STRING_196 = new HttpString("Content-Type");
    } 
    STATE_BYTES_197 = "Date".getBytes("ISO-8859-1");
    if (map.get("Date") != null) {
      HTTP_STRING_198 = map.get("Date");
    } else {
      map.get("Date");
      HTTP_STRING_198 = new HttpString("Date");
    } 
    STATE_BYTES_199 = "Date".getBytes("ISO-8859-1");
    if (map.get("Date") != null) {
      HTTP_STRING_200 = map.get("Date");
    } else {
      map.get("Date");
      HTTP_STRING_200 = new HttpString("Date");
    } 
    STATE_BYTES_201 = "Date".getBytes("ISO-8859-1");
    if (map.get("Date") != null) {
      HTTP_STRING_202 = map.get("Date");
    } else {
      map.get("Date");
      HTTP_STRING_202 = new HttpString("Date");
    } 
    STATE_BYTES_203 = "Date".getBytes("ISO-8859-1");
    if (map.get("Date") != null) {
      HTTP_STRING_204 = map.get("Date");
    } else {
      map.get("Date");
      HTTP_STRING_204 = new HttpString("Date");
    } 
    if (map.get("E") != null) {
      HTTP_STRING_205 = map.get("E");
    } else {
      map.get("E");
      HTTP_STRING_205 = new HttpString("E");
    } 
    STATE_BYTES_206 = "Expires".getBytes("ISO-8859-1");
    if (map.get("Expires") != null) {
      HTTP_STRING_207 = map.get("Expires");
    } else {
      map.get("Expires");
      HTTP_STRING_207 = new HttpString("Expires");
    } 
    STATE_BYTES_208 = "Expires".getBytes("ISO-8859-1");
    if (map.get("Expires") != null) {
      HTTP_STRING_209 = map.get("Expires");
    } else {
      map.get("Expires");
      HTTP_STRING_209 = new HttpString("Expires");
    } 
    STATE_BYTES_210 = "Expires".getBytes("ISO-8859-1");
    if (map.get("Expires") != null) {
      HTTP_STRING_211 = map.get("Expires");
    } else {
      map.get("Expires");
      HTTP_STRING_211 = new HttpString("Expires");
    } 
    STATE_BYTES_212 = "Expires".getBytes("ISO-8859-1");
    if (map.get("Expires") != null) {
      HTTP_STRING_213 = map.get("Expires");
    } else {
      map.get("Expires");
      HTTP_STRING_213 = new HttpString("Expires");
    } 
    STATE_BYTES_214 = "Expires".getBytes("ISO-8859-1");
    if (map.get("Expires") != null) {
      HTTP_STRING_215 = map.get("Expires");
    } else {
      map.get("Expires");
      HTTP_STRING_215 = new HttpString("Expires");
    } 
    STATE_BYTES_216 = "Expires".getBytes("ISO-8859-1");
    if (map.get("Expires") != null) {
      HTTP_STRING_217 = map.get("Expires");
    } else {
      map.get("Expires");
      HTTP_STRING_217 = new HttpString("Expires");
    } 
    STATE_BYTES_218 = "ETag".getBytes("ISO-8859-1");
    if (map.get("ETag") != null) {
      HTTP_STRING_219 = map.get("ETag");
    } else {
      map.get("ETag");
      HTTP_STRING_219 = new HttpString("ETag");
    } 
    STATE_BYTES_220 = "ETag".getBytes("ISO-8859-1");
    if (map.get("ETag") != null) {
      HTTP_STRING_221 = map.get("ETag");
    } else {
      map.get("ETag");
      HTTP_STRING_221 = new HttpString("ETag");
    } 
    STATE_BYTES_222 = "ETag".getBytes("ISO-8859-1");
    if (map.get("ETag") != null) {
      HTTP_STRING_223 = map.get("ETag");
    } else {
      map.get("ETag");
      HTTP_STRING_223 = new HttpString("ETag");
    } 
    if (map.get("L") != null) {
      HTTP_STRING_224 = map.get("L");
    } else {
      map.get("L");
      HTTP_STRING_224 = new HttpString("L");
    } 
    STATE_BYTES_225 = "Last-Modified".getBytes("ISO-8859-1");
    if (map.get("Last-Modified") != null) {
      HTTP_STRING_226 = map.get("Last-Modified");
    } else {
      map.get("Last-Modified");
      HTTP_STRING_226 = new HttpString("Last-Modified");
    } 
    STATE_BYTES_227 = "Last-Modified".getBytes("ISO-8859-1");
    if (map.get("Last-Modified") != null) {
      HTTP_STRING_228 = map.get("Last-Modified");
    } else {
      map.get("Last-Modified");
      HTTP_STRING_228 = new HttpString("Last-Modified");
    } 
    STATE_BYTES_229 = "Last-Modified".getBytes("ISO-8859-1");
    if (map.get("Last-Modified") != null) {
      HTTP_STRING_230 = map.get("Last-Modified");
    } else {
      map.get("Last-Modified");
      HTTP_STRING_230 = new HttpString("Last-Modified");
    } 
    STATE_BYTES_231 = "Last-Modified".getBytes("ISO-8859-1");
    if (map.get("Last-Modified") != null) {
      HTTP_STRING_232 = map.get("Last-Modified");
    } else {
      map.get("Last-Modified");
      HTTP_STRING_232 = new HttpString("Last-Modified");
    } 
    STATE_BYTES_233 = "Last-Modified".getBytes("ISO-8859-1");
    if (map.get("Last-Modified") != null) {
      HTTP_STRING_234 = map.get("Last-Modified");
    } else {
      map.get("Last-Modified");
      HTTP_STRING_234 = new HttpString("Last-Modified");
    } 
    STATE_BYTES_235 = "Last-Modified".getBytes("ISO-8859-1");
    if (map.get("Last-Modified") != null) {
      HTTP_STRING_236 = map.get("Last-Modified");
    } else {
      map.get("Last-Modified");
      HTTP_STRING_236 = new HttpString("Last-Modified");
    } 
    STATE_BYTES_237 = "Last-Modified".getBytes("ISO-8859-1");
    if (map.get("Last-Modified") != null) {
      HTTP_STRING_238 = map.get("Last-Modified");
    } else {
      map.get("Last-Modified");
      HTTP_STRING_238 = new HttpString("Last-Modified");
    } 
    STATE_BYTES_239 = "Last-Modified".getBytes("ISO-8859-1");
    if (map.get("Last-Modified") != null) {
      HTTP_STRING_240 = map.get("Last-Modified");
    } else {
      map.get("Last-Modified");
      HTTP_STRING_240 = new HttpString("Last-Modified");
    } 
    STATE_BYTES_241 = "Last-Modified".getBytes("ISO-8859-1");
    if (map.get("Last-Modified") != null) {
      HTTP_STRING_242 = map.get("Last-Modified");
    } else {
      map.get("Last-Modified");
      HTTP_STRING_242 = new HttpString("Last-Modified");
    } 
    STATE_BYTES_243 = "Last-Modified".getBytes("ISO-8859-1");
    if (map.get("Last-Modified") != null) {
      HTTP_STRING_244 = map.get("Last-Modified");
    } else {
      map.get("Last-Modified");
      HTTP_STRING_244 = new HttpString("Last-Modified");
    } 
    STATE_BYTES_245 = "Last-Modified".getBytes("ISO-8859-1");
    if (map.get("Last-Modified") != null) {
      HTTP_STRING_246 = map.get("Last-Modified");
    } else {
      map.get("Last-Modified");
      HTTP_STRING_246 = new HttpString("Last-Modified");
    } 
    STATE_BYTES_247 = "Last-Modified".getBytes("ISO-8859-1");
    if (map.get("Last-Modified") != null) {
      HTTP_STRING_248 = map.get("Last-Modified");
    } else {
      map.get("Last-Modified");
      HTTP_STRING_248 = new HttpString("Last-Modified");
    } 
    STATE_BYTES_249 = "Location".getBytes("ISO-8859-1");
    if (map.get("Location") != null) {
      HTTP_STRING_250 = map.get("Location");
    } else {
      map.get("Location");
      HTTP_STRING_250 = new HttpString("Location");
    } 
    STATE_BYTES_251 = "Location".getBytes("ISO-8859-1");
    if (map.get("Location") != null) {
      HTTP_STRING_252 = map.get("Location");
    } else {
      map.get("Location");
      HTTP_STRING_252 = new HttpString("Location");
    } 
    STATE_BYTES_253 = "Location".getBytes("ISO-8859-1");
    if (map.get("Location") != null) {
      HTTP_STRING_254 = map.get("Location");
    } else {
      map.get("Location");
      HTTP_STRING_254 = new HttpString("Location");
    } 
    STATE_BYTES_255 = "Location".getBytes("ISO-8859-1");
    if (map.get("Location") != null) {
      HTTP_STRING_256 = map.get("Location");
    } else {
      map.get("Location");
      HTTP_STRING_256 = new HttpString("Location");
    } 
    STATE_BYTES_257 = "Location".getBytes("ISO-8859-1");
    if (map.get("Location") != null) {
      HTTP_STRING_258 = map.get("Location");
    } else {
      map.get("Location");
      HTTP_STRING_258 = new HttpString("Location");
    } 
    STATE_BYTES_259 = "Location".getBytes("ISO-8859-1");
    if (map.get("Location") != null) {
      HTTP_STRING_260 = map.get("Location");
    } else {
      map.get("Location");
      HTTP_STRING_260 = new HttpString("Location");
    } 
    STATE_BYTES_261 = "Location".getBytes("ISO-8859-1");
    if (map.get("Location") != null) {
      HTTP_STRING_262 = map.get("Location");
    } else {
      map.get("Location");
      HTTP_STRING_262 = new HttpString("Location");
    } 
    if (map.get("P") != null) {
      HTTP_STRING_263 = map.get("P");
    } else {
      map.get("P");
      HTTP_STRING_263 = new HttpString("P");
    } 
    if (map.get("Pr") != null) {
      HTTP_STRING_264 = map.get("Pr");
    } else {
      map.get("Pr");
      HTTP_STRING_264 = new HttpString("Pr");
    } 
    STATE_BYTES_265 = "Pragma".getBytes("ISO-8859-1");
    if (map.get("Pragma") != null) {
      HTTP_STRING_266 = map.get("Pragma");
    } else {
      map.get("Pragma");
      HTTP_STRING_266 = new HttpString("Pragma");
    } 
    STATE_BYTES_267 = "Pragma".getBytes("ISO-8859-1");
    if (map.get("Pragma") != null) {
      HTTP_STRING_268 = map.get("Pragma");
    } else {
      map.get("Pragma");
      HTTP_STRING_268 = new HttpString("Pragma");
    } 
    STATE_BYTES_269 = "Pragma".getBytes("ISO-8859-1");
    if (map.get("Pragma") != null) {
      HTTP_STRING_270 = map.get("Pragma");
    } else {
      map.get("Pragma");
      HTTP_STRING_270 = new HttpString("Pragma");
    } 
    STATE_BYTES_271 = "Pragma".getBytes("ISO-8859-1");
    if (map.get("Pragma") != null) {
      HTTP_STRING_272 = map.get("Pragma");
    } else {
      map.get("Pragma");
      HTTP_STRING_272 = new HttpString("Pragma");
    } 
    STATE_BYTES_273 = "Proxy-Authenticate".getBytes("ISO-8859-1");
    if (map.get("Proxy-Authenticate") != null) {
      HTTP_STRING_274 = map.get("Proxy-Authenticate");
    } else {
      map.get("Proxy-Authenticate");
      HTTP_STRING_274 = new HttpString("Proxy-Authenticate");
    } 
    STATE_BYTES_275 = "Proxy-Authenticate".getBytes("ISO-8859-1");
    if (map.get("Proxy-Authenticate") != null) {
      HTTP_STRING_276 = map.get("Proxy-Authenticate");
    } else {
      map.get("Proxy-Authenticate");
      HTTP_STRING_276 = new HttpString("Proxy-Authenticate");
    } 
    STATE_BYTES_277 = "Proxy-Authenticate".getBytes("ISO-8859-1");
    if (map.get("Proxy-Authenticate") != null) {
      HTTP_STRING_278 = map.get("Proxy-Authenticate");
    } else {
      map.get("Proxy-Authenticate");
      HTTP_STRING_278 = new HttpString("Proxy-Authenticate");
    } 
    STATE_BYTES_279 = "Proxy-Authenticate".getBytes("ISO-8859-1");
    if (map.get("Proxy-Authenticate") != null) {
      HTTP_STRING_280 = map.get("Proxy-Authenticate");
    } else {
      map.get("Proxy-Authenticate");
      HTTP_STRING_280 = new HttpString("Proxy-Authenticate");
    } 
    STATE_BYTES_281 = "Proxy-Authenticate".getBytes("ISO-8859-1");
    if (map.get("Proxy-Authenticate") != null) {
      HTTP_STRING_282 = map.get("Proxy-Authenticate");
    } else {
      map.get("Proxy-Authenticate");
      HTTP_STRING_282 = new HttpString("Proxy-Authenticate");
    } 
    STATE_BYTES_283 = "Proxy-Authenticate".getBytes("ISO-8859-1");
    if (map.get("Proxy-Authenticate") != null) {
      HTTP_STRING_284 = map.get("Proxy-Authenticate");
    } else {
      map.get("Proxy-Authenticate");
      HTTP_STRING_284 = new HttpString("Proxy-Authenticate");
    } 
    STATE_BYTES_285 = "Proxy-Authenticate".getBytes("ISO-8859-1");
    if (map.get("Proxy-Authenticate") != null) {
      HTTP_STRING_286 = map.get("Proxy-Authenticate");
    } else {
      map.get("Proxy-Authenticate");
      HTTP_STRING_286 = new HttpString("Proxy-Authenticate");
    } 
    STATE_BYTES_287 = "Proxy-Authenticate".getBytes("ISO-8859-1");
    if (map.get("Proxy-Authenticate") != null) {
      HTTP_STRING_288 = map.get("Proxy-Authenticate");
    } else {
      map.get("Proxy-Authenticate");
      HTTP_STRING_288 = new HttpString("Proxy-Authenticate");
    } 
    STATE_BYTES_289 = "Proxy-Authenticate".getBytes("ISO-8859-1");
    if (map.get("Proxy-Authenticate") != null) {
      HTTP_STRING_290 = map.get("Proxy-Authenticate");
    } else {
      map.get("Proxy-Authenticate");
      HTTP_STRING_290 = new HttpString("Proxy-Authenticate");
    } 
    STATE_BYTES_291 = "Proxy-Authenticate".getBytes("ISO-8859-1");
    if (map.get("Proxy-Authenticate") != null) {
      HTTP_STRING_292 = map.get("Proxy-Authenticate");
    } else {
      map.get("Proxy-Authenticate");
      HTTP_STRING_292 = new HttpString("Proxy-Authenticate");
    } 
    STATE_BYTES_293 = "Proxy-Authenticate".getBytes("ISO-8859-1");
    if (map.get("Proxy-Authenticate") != null) {
      HTTP_STRING_294 = map.get("Proxy-Authenticate");
    } else {
      map.get("Proxy-Authenticate");
      HTTP_STRING_294 = new HttpString("Proxy-Authenticate");
    } 
    STATE_BYTES_295 = "Proxy-Authenticate".getBytes("ISO-8859-1");
    if (map.get("Proxy-Authenticate") != null) {
      HTTP_STRING_296 = map.get("Proxy-Authenticate");
    } else {
      map.get("Proxy-Authenticate");
      HTTP_STRING_296 = new HttpString("Proxy-Authenticate");
    } 
    STATE_BYTES_297 = "Proxy-Authenticate".getBytes("ISO-8859-1");
    if (map.get("Proxy-Authenticate") != null) {
      HTTP_STRING_298 = map.get("Proxy-Authenticate");
    } else {
      map.get("Proxy-Authenticate");
      HTTP_STRING_298 = new HttpString("Proxy-Authenticate");
    } 
    STATE_BYTES_299 = "Proxy-Authenticate".getBytes("ISO-8859-1");
    if (map.get("Proxy-Authenticate") != null) {
      HTTP_STRING_300 = map.get("Proxy-Authenticate");
    } else {
      map.get("Proxy-Authenticate");
      HTTP_STRING_300 = new HttpString("Proxy-Authenticate");
    } 
    STATE_BYTES_301 = "Proxy-Authenticate".getBytes("ISO-8859-1");
    if (map.get("Proxy-Authenticate") != null) {
      HTTP_STRING_302 = map.get("Proxy-Authenticate");
    } else {
      map.get("Proxy-Authenticate");
      HTTP_STRING_302 = new HttpString("Proxy-Authenticate");
    } 
    STATE_BYTES_303 = "Proxy-Authenticate".getBytes("ISO-8859-1");
    if (map.get("Proxy-Authenticate") != null) {
      HTTP_STRING_304 = map.get("Proxy-Authenticate");
    } else {
      map.get("Proxy-Authenticate");
      HTTP_STRING_304 = new HttpString("Proxy-Authenticate");
    } 
    if (map.get("R") != null) {
      HTTP_STRING_305 = map.get("R");
    } else {
      map.get("R");
      HTTP_STRING_305 = new HttpString("R");
    } 
    if (map.get("Re") != null) {
      HTTP_STRING_306 = map.get("Re");
    } else {
      map.get("Re");
      HTTP_STRING_306 = new HttpString("Re");
    } 
    STATE_BYTES_307 = "Refresh".getBytes("ISO-8859-1");
    if (map.get("Refresh") != null) {
      HTTP_STRING_308 = map.get("Refresh");
    } else {
      map.get("Refresh");
      HTTP_STRING_308 = new HttpString("Refresh");
    } 
    STATE_BYTES_309 = "Refresh".getBytes("ISO-8859-1");
    if (map.get("Refresh") != null) {
      HTTP_STRING_310 = map.get("Refresh");
    } else {
      map.get("Refresh");
      HTTP_STRING_310 = new HttpString("Refresh");
    } 
    STATE_BYTES_311 = "Refresh".getBytes("ISO-8859-1");
    if (map.get("Refresh") != null) {
      HTTP_STRING_312 = map.get("Refresh");
    } else {
      map.get("Refresh");
      HTTP_STRING_312 = new HttpString("Refresh");
    } 
    STATE_BYTES_313 = "Refresh".getBytes("ISO-8859-1");
    if (map.get("Refresh") != null) {
      HTTP_STRING_314 = map.get("Refresh");
    } else {
      map.get("Refresh");
      HTTP_STRING_314 = new HttpString("Refresh");
    } 
    STATE_BYTES_315 = "Refresh".getBytes("ISO-8859-1");
    if (map.get("Refresh") != null) {
      HTTP_STRING_316 = map.get("Refresh");
    } else {
      map.get("Refresh");
      HTTP_STRING_316 = new HttpString("Refresh");
    } 
    STATE_BYTES_317 = "Retry-After".getBytes("ISO-8859-1");
    if (map.get("Retry-After") != null) {
      HTTP_STRING_318 = map.get("Retry-After");
    } else {
      map.get("Retry-After");
      HTTP_STRING_318 = new HttpString("Retry-After");
    } 
    STATE_BYTES_319 = "Retry-After".getBytes("ISO-8859-1");
    if (map.get("Retry-After") != null) {
      HTTP_STRING_320 = map.get("Retry-After");
    } else {
      map.get("Retry-After");
      HTTP_STRING_320 = new HttpString("Retry-After");
    } 
    STATE_BYTES_321 = "Retry-After".getBytes("ISO-8859-1");
    if (map.get("Retry-After") != null) {
      HTTP_STRING_322 = map.get("Retry-After");
    } else {
      map.get("Retry-After");
      HTTP_STRING_322 = new HttpString("Retry-After");
    } 
    STATE_BYTES_323 = "Retry-After".getBytes("ISO-8859-1");
    if (map.get("Retry-After") != null) {
      HTTP_STRING_324 = map.get("Retry-After");
    } else {
      map.get("Retry-After");
      HTTP_STRING_324 = new HttpString("Retry-After");
    } 
    STATE_BYTES_325 = "Retry-After".getBytes("ISO-8859-1");
    if (map.get("Retry-After") != null) {
      HTTP_STRING_326 = map.get("Retry-After");
    } else {
      map.get("Retry-After");
      HTTP_STRING_326 = new HttpString("Retry-After");
    } 
    STATE_BYTES_327 = "Retry-After".getBytes("ISO-8859-1");
    if (map.get("Retry-After") != null) {
      HTTP_STRING_328 = map.get("Retry-After");
    } else {
      map.get("Retry-After");
      HTTP_STRING_328 = new HttpString("Retry-After");
    } 
    STATE_BYTES_329 = "Retry-After".getBytes("ISO-8859-1");
    if (map.get("Retry-After") != null) {
      HTTP_STRING_330 = map.get("Retry-After");
    } else {
      map.get("Retry-After");
      HTTP_STRING_330 = new HttpString("Retry-After");
    } 
    STATE_BYTES_331 = "Retry-After".getBytes("ISO-8859-1");
    if (map.get("Retry-After") != null) {
      HTTP_STRING_332 = map.get("Retry-After");
    } else {
      map.get("Retry-After");
      HTTP_STRING_332 = new HttpString("Retry-After");
    } 
    STATE_BYTES_333 = "Retry-After".getBytes("ISO-8859-1");
    if (map.get("Retry-After") != null) {
      HTTP_STRING_334 = map.get("Retry-After");
    } else {
      map.get("Retry-After");
      HTTP_STRING_334 = new HttpString("Retry-After");
    } 
    if (map.get("S") != null) {
      HTTP_STRING_335 = map.get("S");
    } else {
      map.get("S");
      HTTP_STRING_335 = new HttpString("S");
    } 
    if (map.get("Se") != null) {
      HTTP_STRING_336 = map.get("Se");
    } else {
      map.get("Se");
      HTTP_STRING_336 = new HttpString("Se");
    } 
    STATE_BYTES_337 = "Server".getBytes("ISO-8859-1");
    if (map.get("Server") != null) {
      HTTP_STRING_338 = map.get("Server");
    } else {
      map.get("Server");
      HTTP_STRING_338 = new HttpString("Server");
    } 
    STATE_BYTES_339 = "Server".getBytes("ISO-8859-1");
    if (map.get("Server") != null) {
      HTTP_STRING_340 = map.get("Server");
    } else {
      map.get("Server");
      HTTP_STRING_340 = new HttpString("Server");
    } 
    STATE_BYTES_341 = "Server".getBytes("ISO-8859-1");
    if (map.get("Server") != null) {
      HTTP_STRING_342 = map.get("Server");
    } else {
      map.get("Server");
      HTTP_STRING_342 = new HttpString("Server");
    } 
    STATE_BYTES_343 = "Server".getBytes("ISO-8859-1");
    if (map.get("Server") != null) {
      HTTP_STRING_344 = map.get("Server");
    } else {
      map.get("Server");
      HTTP_STRING_344 = new HttpString("Server");
    } 
    STATE_BYTES_345 = "Set-Cookie2".getBytes("ISO-8859-1");
    if (map.get("Set-Cookie2") != null) {
      HTTP_STRING_346 = map.get("Set-Cookie2");
    } else {
      map.get("Set-Cookie2");
      HTTP_STRING_346 = new HttpString("Set-Cookie2");
    } 
    STATE_BYTES_347 = "Set-Cookie2".getBytes("ISO-8859-1");
    if (map.get("Set-Cookie2") != null) {
      HTTP_STRING_348 = map.get("Set-Cookie2");
    } else {
      map.get("Set-Cookie2");
      HTTP_STRING_348 = new HttpString("Set-Cookie2");
    } 
    STATE_BYTES_349 = "Set-Cookie2".getBytes("ISO-8859-1");
    if (map.get("Set-Cookie2") != null) {
      HTTP_STRING_350 = map.get("Set-Cookie2");
    } else {
      map.get("Set-Cookie2");
      HTTP_STRING_350 = new HttpString("Set-Cookie2");
    } 
    STATE_BYTES_351 = "Set-Cookie2".getBytes("ISO-8859-1");
    if (map.get("Set-Cookie2") != null) {
      HTTP_STRING_352 = map.get("Set-Cookie2");
    } else {
      map.get("Set-Cookie2");
      HTTP_STRING_352 = new HttpString("Set-Cookie2");
    } 
    STATE_BYTES_353 = "Set-Cookie2".getBytes("ISO-8859-1");
    if (map.get("Set-Cookie2") != null) {
      HTTP_STRING_354 = map.get("Set-Cookie2");
    } else {
      map.get("Set-Cookie2");
      HTTP_STRING_354 = new HttpString("Set-Cookie2");
    } 
    STATE_BYTES_355 = "Set-Cookie2".getBytes("ISO-8859-1");
    if (map.get("Set-Cookie2") != null) {
      HTTP_STRING_356 = map.get("Set-Cookie2");
    } else {
      map.get("Set-Cookie2");
      HTTP_STRING_356 = new HttpString("Set-Cookie2");
    } 
    STATE_BYTES_357 = "Set-Cookie2".getBytes("ISO-8859-1");
    if (map.get("Set-Cookie2") != null) {
      HTTP_STRING_358 = map.get("Set-Cookie2");
    } else {
      map.get("Set-Cookie2");
      HTTP_STRING_358 = new HttpString("Set-Cookie2");
    } 
    STATE_BYTES_359 = "Set-Cookie2".getBytes("ISO-8859-1");
    if (map.get("Set-Cookie2") != null) {
      HTTP_STRING_360 = map.get("Set-Cookie2");
    } else {
      map.get("Set-Cookie2");
      HTTP_STRING_360 = new HttpString("Set-Cookie2");
    } 
    STATE_BYTES_361 = "Set-Cookie2".getBytes("ISO-8859-1");
    if (map.get("Set-Cookie2") != null) {
      HTTP_STRING_362 = map.get("Set-Cookie2");
    } else {
      map.get("Set-Cookie2");
      HTTP_STRING_362 = new HttpString("Set-Cookie2");
    } 
    STATE_BYTES_363 = "Strict-Transport-Security".getBytes("ISO-8859-1");
    if (map.get("Strict-Transport-Security") != null) {
      HTTP_STRING_364 = map.get("Strict-Transport-Security");
    } else {
      map.get("Strict-Transport-Security");
      HTTP_STRING_364 = new HttpString("Strict-Transport-Security");
    } 
    STATE_BYTES_365 = "Strict-Transport-Security".getBytes("ISO-8859-1");
    if (map.get("Strict-Transport-Security") != null) {
      HTTP_STRING_366 = map.get("Strict-Transport-Security");
    } else {
      map.get("Strict-Transport-Security");
      HTTP_STRING_366 = new HttpString("Strict-Transport-Security");
    } 
    STATE_BYTES_367 = "Strict-Transport-Security".getBytes("ISO-8859-1");
    if (map.get("Strict-Transport-Security") != null) {
      HTTP_STRING_368 = map.get("Strict-Transport-Security");
    } else {
      map.get("Strict-Transport-Security");
      HTTP_STRING_368 = new HttpString("Strict-Transport-Security");
    } 
    STATE_BYTES_369 = "Strict-Transport-Security".getBytes("ISO-8859-1");
    if (map.get("Strict-Transport-Security") != null) {
      HTTP_STRING_370 = map.get("Strict-Transport-Security");
    } else {
      map.get("Strict-Transport-Security");
      HTTP_STRING_370 = new HttpString("Strict-Transport-Security");
    } 
    STATE_BYTES_371 = "Strict-Transport-Security".getBytes("ISO-8859-1");
    if (map.get("Strict-Transport-Security") != null) {
      HTTP_STRING_372 = map.get("Strict-Transport-Security");
    } else {
      map.get("Strict-Transport-Security");
      HTTP_STRING_372 = new HttpString("Strict-Transport-Security");
    } 
    STATE_BYTES_373 = "Strict-Transport-Security".getBytes("ISO-8859-1");
    if (map.get("Strict-Transport-Security") != null) {
      HTTP_STRING_374 = map.get("Strict-Transport-Security");
    } else {
      map.get("Strict-Transport-Security");
      HTTP_STRING_374 = new HttpString("Strict-Transport-Security");
    } 
    STATE_BYTES_375 = "Strict-Transport-Security".getBytes("ISO-8859-1");
    if (map.get("Strict-Transport-Security") != null) {
      HTTP_STRING_376 = map.get("Strict-Transport-Security");
    } else {
      map.get("Strict-Transport-Security");
      HTTP_STRING_376 = new HttpString("Strict-Transport-Security");
    } 
    STATE_BYTES_377 = "Strict-Transport-Security".getBytes("ISO-8859-1");
    if (map.get("Strict-Transport-Security") != null) {
      HTTP_STRING_378 = map.get("Strict-Transport-Security");
    } else {
      map.get("Strict-Transport-Security");
      HTTP_STRING_378 = new HttpString("Strict-Transport-Security");
    } 
    STATE_BYTES_379 = "Strict-Transport-Security".getBytes("ISO-8859-1");
    if (map.get("Strict-Transport-Security") != null) {
      HTTP_STRING_380 = map.get("Strict-Transport-Security");
    } else {
      map.get("Strict-Transport-Security");
      HTTP_STRING_380 = new HttpString("Strict-Transport-Security");
    } 
    STATE_BYTES_381 = "Strict-Transport-Security".getBytes("ISO-8859-1");
    if (map.get("Strict-Transport-Security") != null) {
      HTTP_STRING_382 = map.get("Strict-Transport-Security");
    } else {
      map.get("Strict-Transport-Security");
      HTTP_STRING_382 = new HttpString("Strict-Transport-Security");
    } 
    STATE_BYTES_383 = "Strict-Transport-Security".getBytes("ISO-8859-1");
    if (map.get("Strict-Transport-Security") != null) {
      HTTP_STRING_384 = map.get("Strict-Transport-Security");
    } else {
      map.get("Strict-Transport-Security");
      HTTP_STRING_384 = new HttpString("Strict-Transport-Security");
    } 
    STATE_BYTES_385 = "Strict-Transport-Security".getBytes("ISO-8859-1");
    if (map.get("Strict-Transport-Security") != null) {
      HTTP_STRING_386 = map.get("Strict-Transport-Security");
    } else {
      map.get("Strict-Transport-Security");
      HTTP_STRING_386 = new HttpString("Strict-Transport-Security");
    } 
    STATE_BYTES_387 = "Strict-Transport-Security".getBytes("ISO-8859-1");
    if (map.get("Strict-Transport-Security") != null) {
      HTTP_STRING_388 = map.get("Strict-Transport-Security");
    } else {
      map.get("Strict-Transport-Security");
      HTTP_STRING_388 = new HttpString("Strict-Transport-Security");
    } 
    STATE_BYTES_389 = "Strict-Transport-Security".getBytes("ISO-8859-1");
    if (map.get("Strict-Transport-Security") != null) {
      HTTP_STRING_390 = map.get("Strict-Transport-Security");
    } else {
      map.get("Strict-Transport-Security");
      HTTP_STRING_390 = new HttpString("Strict-Transport-Security");
    } 
    STATE_BYTES_391 = "Strict-Transport-Security".getBytes("ISO-8859-1");
    if (map.get("Strict-Transport-Security") != null) {
      HTTP_STRING_392 = map.get("Strict-Transport-Security");
    } else {
      map.get("Strict-Transport-Security");
      HTTP_STRING_392 = new HttpString("Strict-Transport-Security");
    } 
    STATE_BYTES_393 = "Strict-Transport-Security".getBytes("ISO-8859-1");
    if (map.get("Strict-Transport-Security") != null) {
      HTTP_STRING_394 = map.get("Strict-Transport-Security");
    } else {
      map.get("Strict-Transport-Security");
      HTTP_STRING_394 = new HttpString("Strict-Transport-Security");
    } 
    STATE_BYTES_395 = "Strict-Transport-Security".getBytes("ISO-8859-1");
    if (map.get("Strict-Transport-Security") != null) {
      HTTP_STRING_396 = map.get("Strict-Transport-Security");
    } else {
      map.get("Strict-Transport-Security");
      HTTP_STRING_396 = new HttpString("Strict-Transport-Security");
    } 
    STATE_BYTES_397 = "Strict-Transport-Security".getBytes("ISO-8859-1");
    if (map.get("Strict-Transport-Security") != null) {
      HTTP_STRING_398 = map.get("Strict-Transport-Security");
    } else {
      map.get("Strict-Transport-Security");
      HTTP_STRING_398 = new HttpString("Strict-Transport-Security");
    } 
    STATE_BYTES_399 = "Strict-Transport-Security".getBytes("ISO-8859-1");
    if (map.get("Strict-Transport-Security") != null) {
      HTTP_STRING_400 = map.get("Strict-Transport-Security");
    } else {
      map.get("Strict-Transport-Security");
      HTTP_STRING_400 = new HttpString("Strict-Transport-Security");
    } 
    STATE_BYTES_401 = "Strict-Transport-Security".getBytes("ISO-8859-1");
    if (map.get("Strict-Transport-Security") != null) {
      HTTP_STRING_402 = map.get("Strict-Transport-Security");
    } else {
      map.get("Strict-Transport-Security");
      HTTP_STRING_402 = new HttpString("Strict-Transport-Security");
    } 
    STATE_BYTES_403 = "Strict-Transport-Security".getBytes("ISO-8859-1");
    if (map.get("Strict-Transport-Security") != null) {
      HTTP_STRING_404 = map.get("Strict-Transport-Security");
    } else {
      map.get("Strict-Transport-Security");
      HTTP_STRING_404 = new HttpString("Strict-Transport-Security");
    } 
    STATE_BYTES_405 = "Strict-Transport-Security".getBytes("ISO-8859-1");
    if (map.get("Strict-Transport-Security") != null) {
      HTTP_STRING_406 = map.get("Strict-Transport-Security");
    } else {
      map.get("Strict-Transport-Security");
      HTTP_STRING_406 = new HttpString("Strict-Transport-Security");
    } 
    STATE_BYTES_407 = "Strict-Transport-Security".getBytes("ISO-8859-1");
    if (map.get("Strict-Transport-Security") != null) {
      HTTP_STRING_408 = map.get("Strict-Transport-Security");
    } else {
      map.get("Strict-Transport-Security");
      HTTP_STRING_408 = new HttpString("Strict-Transport-Security");
    } 
    STATE_BYTES_409 = "Strict-Transport-Security".getBytes("ISO-8859-1");
    if (map.get("Strict-Transport-Security") != null) {
      HTTP_STRING_410 = map.get("Strict-Transport-Security");
    } else {
      map.get("Strict-Transport-Security");
      HTTP_STRING_410 = new HttpString("Strict-Transport-Security");
    } 
    if (map.get("T") != null) {
      HTTP_STRING_411 = map.get("T");
    } else {
      map.get("T");
      HTTP_STRING_411 = new HttpString("T");
    } 
    if (map.get("Tr") != null) {
      HTTP_STRING_412 = map.get("Tr");
    } else {
      map.get("Tr");
      HTTP_STRING_412 = new HttpString("Tr");
    } 
    if (map.get("Tra") != null) {
      HTTP_STRING_413 = map.get("Tra");
    } else {
      map.get("Tra");
      HTTP_STRING_413 = new HttpString("Tra");
    } 
    STATE_BYTES_414 = "Trailer".getBytes("ISO-8859-1");
    if (map.get("Trailer") != null) {
      HTTP_STRING_415 = map.get("Trailer");
    } else {
      map.get("Trailer");
      HTTP_STRING_415 = new HttpString("Trailer");
    } 
    STATE_BYTES_416 = "Trailer".getBytes("ISO-8859-1");
    if (map.get("Trailer") != null) {
      HTTP_STRING_417 = map.get("Trailer");
    } else {
      map.get("Trailer");
      HTTP_STRING_417 = new HttpString("Trailer");
    } 
    STATE_BYTES_418 = "Trailer".getBytes("ISO-8859-1");
    if (map.get("Trailer") != null) {
      HTTP_STRING_419 = map.get("Trailer");
    } else {
      map.get("Trailer");
      HTTP_STRING_419 = new HttpString("Trailer");
    } 
    STATE_BYTES_420 = "Trailer".getBytes("ISO-8859-1");
    if (map.get("Trailer") != null) {
      HTTP_STRING_421 = map.get("Trailer");
    } else {
      map.get("Trailer");
      HTTP_STRING_421 = new HttpString("Trailer");
    } 
    STATE_BYTES_422 = "Transfer-Encoding".getBytes("ISO-8859-1");
    if (map.get("Transfer-Encoding") != null) {
      HTTP_STRING_423 = map.get("Transfer-Encoding");
    } else {
      map.get("Transfer-Encoding");
      HTTP_STRING_423 = new HttpString("Transfer-Encoding");
    } 
    STATE_BYTES_424 = "Transfer-Encoding".getBytes("ISO-8859-1");
    if (map.get("Transfer-Encoding") != null) {
      HTTP_STRING_425 = map.get("Transfer-Encoding");
    } else {
      map.get("Transfer-Encoding");
      HTTP_STRING_425 = new HttpString("Transfer-Encoding");
    } 
    STATE_BYTES_426 = "Transfer-Encoding".getBytes("ISO-8859-1");
    if (map.get("Transfer-Encoding") != null) {
      HTTP_STRING_427 = map.get("Transfer-Encoding");
    } else {
      map.get("Transfer-Encoding");
      HTTP_STRING_427 = new HttpString("Transfer-Encoding");
    } 
    STATE_BYTES_428 = "Transfer-Encoding".getBytes("ISO-8859-1");
    if (map.get("Transfer-Encoding") != null) {
      HTTP_STRING_429 = map.get("Transfer-Encoding");
    } else {
      map.get("Transfer-Encoding");
      HTTP_STRING_429 = new HttpString("Transfer-Encoding");
    } 
    STATE_BYTES_430 = "Transfer-Encoding".getBytes("ISO-8859-1");
    if (map.get("Transfer-Encoding") != null) {
      HTTP_STRING_431 = map.get("Transfer-Encoding");
    } else {
      map.get("Transfer-Encoding");
      HTTP_STRING_431 = new HttpString("Transfer-Encoding");
    } 
    STATE_BYTES_432 = "Transfer-Encoding".getBytes("ISO-8859-1");
    if (map.get("Transfer-Encoding") != null) {
      HTTP_STRING_433 = map.get("Transfer-Encoding");
    } else {
      map.get("Transfer-Encoding");
      HTTP_STRING_433 = new HttpString("Transfer-Encoding");
    } 
    STATE_BYTES_434 = "Transfer-Encoding".getBytes("ISO-8859-1");
    if (map.get("Transfer-Encoding") != null) {
      HTTP_STRING_435 = map.get("Transfer-Encoding");
    } else {
      map.get("Transfer-Encoding");
      HTTP_STRING_435 = new HttpString("Transfer-Encoding");
    } 
    STATE_BYTES_436 = "Transfer-Encoding".getBytes("ISO-8859-1");
    if (map.get("Transfer-Encoding") != null) {
      HTTP_STRING_437 = map.get("Transfer-Encoding");
    } else {
      map.get("Transfer-Encoding");
      HTTP_STRING_437 = new HttpString("Transfer-Encoding");
    } 
    STATE_BYTES_438 = "Transfer-Encoding".getBytes("ISO-8859-1");
    if (map.get("Transfer-Encoding") != null) {
      HTTP_STRING_439 = map.get("Transfer-Encoding");
    } else {
      map.get("Transfer-Encoding");
      HTTP_STRING_439 = new HttpString("Transfer-Encoding");
    } 
    STATE_BYTES_440 = "Transfer-Encoding".getBytes("ISO-8859-1");
    if (map.get("Transfer-Encoding") != null) {
      HTTP_STRING_441 = map.get("Transfer-Encoding");
    } else {
      map.get("Transfer-Encoding");
      HTTP_STRING_441 = new HttpString("Transfer-Encoding");
    } 
    STATE_BYTES_442 = "Transfer-Encoding".getBytes("ISO-8859-1");
    if (map.get("Transfer-Encoding") != null) {
      HTTP_STRING_443 = map.get("Transfer-Encoding");
    } else {
      map.get("Transfer-Encoding");
      HTTP_STRING_443 = new HttpString("Transfer-Encoding");
    } 
    STATE_BYTES_444 = "Transfer-Encoding".getBytes("ISO-8859-1");
    if (map.get("Transfer-Encoding") != null) {
      HTTP_STRING_445 = map.get("Transfer-Encoding");
    } else {
      map.get("Transfer-Encoding");
      HTTP_STRING_445 = new HttpString("Transfer-Encoding");
    } 
    STATE_BYTES_446 = "Transfer-Encoding".getBytes("ISO-8859-1");
    if (map.get("Transfer-Encoding") != null) {
      HTTP_STRING_447 = map.get("Transfer-Encoding");
    } else {
      map.get("Transfer-Encoding");
      HTTP_STRING_447 = new HttpString("Transfer-Encoding");
    } 
    STATE_BYTES_448 = "Transfer-Encoding".getBytes("ISO-8859-1");
    if (map.get("Transfer-Encoding") != null) {
      HTTP_STRING_449 = map.get("Transfer-Encoding");
    } else {
      map.get("Transfer-Encoding");
      HTTP_STRING_449 = new HttpString("Transfer-Encoding");
    } 
    if (map.get("V") != null) {
      HTTP_STRING_450 = map.get("V");
    } else {
      map.get("V");
      HTTP_STRING_450 = new HttpString("V");
    } 
    STATE_BYTES_451 = "Vary".getBytes("ISO-8859-1");
    if (map.get("Vary") != null) {
      HTTP_STRING_452 = map.get("Vary");
    } else {
      map.get("Vary");
      HTTP_STRING_452 = new HttpString("Vary");
    } 
    STATE_BYTES_453 = "Vary".getBytes("ISO-8859-1");
    if (map.get("Vary") != null) {
      HTTP_STRING_454 = map.get("Vary");
    } else {
      map.get("Vary");
      HTTP_STRING_454 = new HttpString("Vary");
    } 
    STATE_BYTES_455 = "Vary".getBytes("ISO-8859-1");
    if (map.get("Vary") != null) {
      HTTP_STRING_456 = map.get("Vary");
    } else {
      map.get("Vary");
      HTTP_STRING_456 = new HttpString("Vary");
    } 
    STATE_BYTES_457 = "Via".getBytes("ISO-8859-1");
    if (map.get("Via") != null) {
      HTTP_STRING_458 = map.get("Via");
    } else {
      map.get("Via");
      HTTP_STRING_458 = new HttpString("Via");
    } 
    STATE_BYTES_459 = "Via".getBytes("ISO-8859-1");
    if (map.get("Via") != null) {
      HTTP_STRING_460 = map.get("Via");
    } else {
      map.get("Via");
      HTTP_STRING_460 = new HttpString("Via");
    } 
    if (map.get("W") != null) {
      HTTP_STRING_461 = map.get("W");
    } else {
      map.get("W");
      HTTP_STRING_461 = new HttpString("W");
    } 
    STATE_BYTES_462 = "Warning".getBytes("ISO-8859-1");
    if (map.get("Warning") != null) {
      HTTP_STRING_463 = map.get("Warning");
    } else {
      map.get("Warning");
      HTTP_STRING_463 = new HttpString("Warning");
    } 
    STATE_BYTES_464 = "Warning".getBytes("ISO-8859-1");
    if (map.get("Warning") != null) {
      HTTP_STRING_465 = map.get("Warning");
    } else {
      map.get("Warning");
      HTTP_STRING_465 = new HttpString("Warning");
    } 
    STATE_BYTES_466 = "Warning".getBytes("ISO-8859-1");
    if (map.get("Warning") != null) {
      HTTP_STRING_467 = map.get("Warning");
    } else {
      map.get("Warning");
      HTTP_STRING_467 = new HttpString("Warning");
    } 
    STATE_BYTES_468 = "Warning".getBytes("ISO-8859-1");
    if (map.get("Warning") != null) {
      HTTP_STRING_469 = map.get("Warning");
    } else {
      map.get("Warning");
      HTTP_STRING_469 = new HttpString("Warning");
    } 
    STATE_BYTES_470 = "Warning".getBytes("ISO-8859-1");
    if (map.get("Warning") != null) {
      HTTP_STRING_471 = map.get("Warning");
    } else {
      map.get("Warning");
      HTTP_STRING_471 = new HttpString("Warning");
    } 
    STATE_BYTES_472 = "Warning".getBytes("ISO-8859-1");
    if (map.get("Warning") != null) {
      HTTP_STRING_473 = map.get("Warning");
    } else {
      map.get("Warning");
      HTTP_STRING_473 = new HttpString("Warning");
    } 
    STATE_BYTES_474 = "WWW-Authenticate".getBytes("ISO-8859-1");
    if (map.get("WWW-Authenticate") != null) {
      HTTP_STRING_475 = map.get("WWW-Authenticate");
    } else {
      map.get("WWW-Authenticate");
      HTTP_STRING_475 = new HttpString("WWW-Authenticate");
    } 
    STATE_BYTES_476 = "WWW-Authenticate".getBytes("ISO-8859-1");
    if (map.get("WWW-Authenticate") != null) {
      HTTP_STRING_477 = map.get("WWW-Authenticate");
    } else {
      map.get("WWW-Authenticate");
      HTTP_STRING_477 = new HttpString("WWW-Authenticate");
    } 
    STATE_BYTES_478 = "WWW-Authenticate".getBytes("ISO-8859-1");
    if (map.get("WWW-Authenticate") != null) {
      HTTP_STRING_479 = map.get("WWW-Authenticate");
    } else {
      map.get("WWW-Authenticate");
      HTTP_STRING_479 = new HttpString("WWW-Authenticate");
    } 
    STATE_BYTES_480 = "WWW-Authenticate".getBytes("ISO-8859-1");
    if (map.get("WWW-Authenticate") != null) {
      HTTP_STRING_481 = map.get("WWW-Authenticate");
    } else {
      map.get("WWW-Authenticate");
      HTTP_STRING_481 = new HttpString("WWW-Authenticate");
    } 
    STATE_BYTES_482 = "WWW-Authenticate".getBytes("ISO-8859-1");
    if (map.get("WWW-Authenticate") != null) {
      HTTP_STRING_483 = map.get("WWW-Authenticate");
    } else {
      map.get("WWW-Authenticate");
      HTTP_STRING_483 = new HttpString("WWW-Authenticate");
    } 
    STATE_BYTES_484 = "WWW-Authenticate".getBytes("ISO-8859-1");
    if (map.get("WWW-Authenticate") != null) {
      HTTP_STRING_485 = map.get("WWW-Authenticate");
    } else {
      map.get("WWW-Authenticate");
      HTTP_STRING_485 = new HttpString("WWW-Authenticate");
    } 
    STATE_BYTES_486 = "WWW-Authenticate".getBytes("ISO-8859-1");
    if (map.get("WWW-Authenticate") != null) {
      HTTP_STRING_487 = map.get("WWW-Authenticate");
    } else {
      map.get("WWW-Authenticate");
      HTTP_STRING_487 = new HttpString("WWW-Authenticate");
    } 
    STATE_BYTES_488 = "WWW-Authenticate".getBytes("ISO-8859-1");
    if (map.get("WWW-Authenticate") != null) {
      HTTP_STRING_489 = map.get("WWW-Authenticate");
    } else {
      map.get("WWW-Authenticate");
      HTTP_STRING_489 = new HttpString("WWW-Authenticate");
    } 
    STATE_BYTES_490 = "WWW-Authenticate".getBytes("ISO-8859-1");
    if (map.get("WWW-Authenticate") != null) {
      HTTP_STRING_491 = map.get("WWW-Authenticate");
    } else {
      map.get("WWW-Authenticate");
      HTTP_STRING_491 = new HttpString("WWW-Authenticate");
    } 
    STATE_BYTES_492 = "WWW-Authenticate".getBytes("ISO-8859-1");
    if (map.get("WWW-Authenticate") != null) {
      HTTP_STRING_493 = map.get("WWW-Authenticate");
    } else {
      map.get("WWW-Authenticate");
      HTTP_STRING_493 = new HttpString("WWW-Authenticate");
    } 
    STATE_BYTES_494 = "WWW-Authenticate".getBytes("ISO-8859-1");
    if (map.get("WWW-Authenticate") != null) {
      HTTP_STRING_495 = map.get("WWW-Authenticate");
    } else {
      map.get("WWW-Authenticate");
      HTTP_STRING_495 = new HttpString("WWW-Authenticate");
    } 
    STATE_BYTES_496 = "WWW-Authenticate".getBytes("ISO-8859-1");
    if (map.get("WWW-Authenticate") != null) {
      HTTP_STRING_497 = map.get("WWW-Authenticate");
    } else {
      map.get("WWW-Authenticate");
      HTTP_STRING_497 = new HttpString("WWW-Authenticate");
    } 
    STATE_BYTES_498 = "WWW-Authenticate".getBytes("ISO-8859-1");
    if (map.get("WWW-Authenticate") != null) {
      HTTP_STRING_499 = map.get("WWW-Authenticate");
    } else {
      map.get("WWW-Authenticate");
      HTTP_STRING_499 = new HttpString("WWW-Authenticate");
    } 
    STATE_BYTES_500 = "WWW-Authenticate".getBytes("ISO-8859-1");
    if (map.get("WWW-Authenticate") != null) {
      HTTP_STRING_501 = map.get("WWW-Authenticate");
    } else {
      map.get("WWW-Authenticate");
      HTTP_STRING_501 = new HttpString("WWW-Authenticate");
    } 
    STATE_BYTES_502 = "WWW-Authenticate".getBytes("ISO-8859-1");
    if (map.get("WWW-Authenticate") != null) {
      HTTP_STRING_503 = map.get("WWW-Authenticate");
    } else {
      map.get("WWW-Authenticate");
      HTTP_STRING_503 = new HttpString("WWW-Authenticate");
    } 
  }
  
  protected final void handleHttpVersion(ByteBuffer paramByteBuffer, ResponseParseState paramResponseParseState, HttpResponseBuilder paramHttpResponseBuilder) throws BadRequestException {
    // Byte code:
    //   0: aload_1
    //   1: invokevirtual hasRemaining : ()Z
    //   4: ifne -> 9
    //   7: iconst_0
    //   8: return
    //   9: aload_2
    //   10: dup
    //   11: getfield stringBuilder : Ljava/lang/StringBuilder;
    //   14: astore #7
    //   16: dup
    //   17: getfield parseState : I
    //   20: dup
    //   21: istore #4
    //   23: ifeq -> 414
    //   26: dup
    //   27: getfield pos : I
    //   30: istore #5
    //   32: dup
    //   33: getfield current : Lio/undertow/util/HttpString;
    //   36: astore #6
    //   38: getfield currentBytes : [B
    //   41: astore #8
    //   43: iload #4
    //   45: tableswitch default -> 100, -2 -> 164, -1 -> 324, 0 -> 424, 1 -> 520, 2 -> 609, 3 -> 698, 4 -> 787, 5 -> 876, 6 -> 994, 7 -> 1084
    //   100: new java/lang/RuntimeException
    //   103: dup
    //   104: ldc 'Invalid character'
    //   106: invokespecial <init> : (Ljava/lang/String;)V
    //   109: athrow
    //   110: aload_2
    //   111: dup
    //   112: dup
    //   113: dup
    //   114: dup
    //   115: iload #5
    //   117: putfield pos : I
    //   120: aload #6
    //   122: putfield current : Lio/undertow/util/HttpString;
    //   125: aload #8
    //   127: putfield currentBytes : [B
    //   130: iload #4
    //   132: putfield parseState : I
    //   135: return
    //   136: aload_2
    //   137: dup
    //   138: dup
    //   139: dup
    //   140: dup
    //   141: iconst_0
    //   142: putfield pos : I
    //   145: aconst_null
    //   146: putfield current : Lio/undertow/util/HttpString;
    //   149: aconst_null
    //   150: putfield currentBytes : [B
    //   153: aload #7
    //   155: iconst_0
    //   156: invokevirtual setLength : (I)V
    //   159: iconst_0
    //   160: putfield parseState : I
    //   163: return
    //   164: aload_1
    //   165: invokevirtual hasRemaining : ()Z
    //   168: ifeq -> 110
    //   171: aload_1
    //   172: invokevirtual get : ()B
    //   175: dup
    //   176: dup
    //   177: bipush #32
    //   179: if_icmpeq -> 261
    //   182: dup
    //   183: bipush #13
    //   185: if_icmpeq -> 253
    //   188: dup
    //   189: bipush #10
    //   191: if_icmpeq -> 253
    //   194: aload #8
    //   196: arraylength
    //   197: iload #5
    //   199: if_icmpeq -> 226
    //   202: dup
    //   203: aload #8
    //   205: iload #5
    //   207: baload
    //   208: isub
    //   209: ifne -> 226
    //   212: pop2
    //   213: iinc #5, 1
    //   216: aload_1
    //   217: invokevirtual hasRemaining : ()Z
    //   220: ifeq -> 110
    //   223: goto -> 164
    //   226: iconst_m1
    //   227: istore #4
    //   229: aload #7
    //   231: aload #6
    //   233: invokevirtual toString : ()Ljava/lang/String;
    //   236: iconst_0
    //   237: iload #5
    //   239: invokevirtual substring : (II)Ljava/lang/String;
    //   242: invokevirtual append : (Ljava/lang/String;)Ljava/lang/StringBuilder;
    //   245: swap
    //   246: invokevirtual append : (C)Ljava/lang/StringBuilder;
    //   249: pop2
    //   250: goto -> 324
    //   253: new io/undertow/util/BadRequestException
    //   256: dup
    //   257: invokespecial <init> : ()V
    //   260: athrow
    //   261: iconst_0
    //   262: istore #4
    //   264: aload #8
    //   266: arraylength
    //   267: iload #5
    //   269: if_icmpeq -> 303
    //   272: new io/undertow/util/HttpString
    //   275: dup
    //   276: aload #8
    //   278: iconst_0
    //   279: iload #5
    //   281: invokespecial <init> : ([BII)V
    //   284: aload_3
    //   285: swap
    //   286: invokevirtual setProtocol : (Lio/undertow/util/HttpString;)V
    //   289: pop
    //   290: aload_2
    //   291: swap
    //   292: putfield leftOver : B
    //   295: aload_2
    //   296: iconst_1
    //   297: putfield state : I
    //   300: goto -> 136
    //   303: aload #6
    //   305: aload_3
    //   306: swap
    //   307: invokevirtual setProtocol : (Lio/undertow/util/HttpString;)V
    //   310: pop
    //   311: aload_2
    //   312: swap
    //   313: putfield leftOver : B
    //   316: aload_2
    //   317: iconst_1
    //   318: putfield state : I
    //   321: goto -> 136
    //   324: aload_1
    //   325: invokevirtual hasRemaining : ()Z
    //   328: ifeq -> 110
    //   331: aload_1
    //   332: invokevirtual get : ()B
    //   335: dup
    //   336: bipush #32
    //   338: if_icmpeq -> 383
    //   341: dup
    //   342: bipush #13
    //   344: if_icmpeq -> 375
    //   347: dup
    //   348: bipush #10
    //   350: if_icmpeq -> 375
    //   353: aload #7
    //   355: swap
    //   356: invokevirtual append : (C)Ljava/lang/StringBuilder;
    //   359: pop
    //   360: aload_1
    //   361: invokevirtual hasRemaining : ()Z
    //   364: ifne -> 324
    //   367: aload_2
    //   368: iload #4
    //   370: putfield parseState : I
    //   373: iconst_0
    //   374: return
    //   375: new io/undertow/util/BadRequestException
    //   378: dup
    //   379: invokespecial <init> : ()V
    //   382: athrow
    //   383: aload #7
    //   385: invokevirtual toString : ()Ljava/lang/String;
    //   388: new io/undertow/util/HttpString
    //   391: dup_x1
    //   392: swap
    //   393: invokespecial <init> : (Ljava/lang/String;)V
    //   396: aload_3
    //   397: swap
    //   398: invokevirtual setProtocol : (Lio/undertow/util/HttpString;)V
    //   401: aload_2
    //   402: swap
    //   403: putfield leftOver : B
    //   406: aload_2
    //   407: iconst_1
    //   408: putfield state : I
    //   411: goto -> 136
    //   414: pop
    //   415: iconst_0
    //   416: istore #5
    //   418: aconst_null
    //   419: astore #6
    //   421: aconst_null
    //   422: astore #8
    //   424: aload_2
    //   425: getfield leftOver : B
    //   428: dup
    //   429: ifne -> 447
    //   432: pop
    //   433: aload_1
    //   434: invokevirtual hasRemaining : ()Z
    //   437: ifeq -> 110
    //   440: aload_1
    //   441: invokevirtual get : ()B
    //   444: goto -> 452
    //   447: aload_2
    //   448: iconst_0
    //   449: putfield leftOver : B
    //   452: dup
    //   453: bipush #72
    //   455: if_icmpeq -> 513
    //   458: dup
    //   459: bipush #32
    //   461: if_icmpeq -> 502
    //   464: dup
    //   465: bipush #13
    //   467: if_icmpeq -> 494
    //   470: dup
    //   471: bipush #10
    //   473: if_icmpeq -> 494
    //   476: iconst_m1
    //   477: istore #4
    //   479: aload #7
    //   481: ldc ''
    //   483: invokevirtual append : (Ljava/lang/String;)Ljava/lang/StringBuilder;
    //   486: swap
    //   487: invokevirtual append : (C)Ljava/lang/StringBuilder;
    //   490: pop
    //   491: goto -> 324
    //   494: new io/undertow/util/BadRequestException
    //   497: dup
    //   498: invokespecial <init> : ()V
    //   501: athrow
    //   502: pop
    //   503: aload_1
    //   504: invokevirtual hasRemaining : ()Z
    //   507: ifeq -> 110
    //   510: goto -> 424
    //   513: pop
    //   514: iconst_1
    //   515: istore #4
    //   517: goto -> 520
    //   520: aload_1
    //   521: invokevirtual hasRemaining : ()Z
    //   524: ifeq -> 110
    //   527: aload_1
    //   528: invokevirtual get : ()B
    //   531: dup
    //   532: bipush #84
    //   534: if_icmpeq -> 602
    //   537: dup
    //   538: bipush #32
    //   540: if_icmpeq -> 581
    //   543: dup
    //   544: bipush #13
    //   546: if_icmpeq -> 573
    //   549: dup
    //   550: bipush #10
    //   552: if_icmpeq -> 573
    //   555: iconst_m1
    //   556: istore #4
    //   558: aload #7
    //   560: ldc 'H'
    //   562: invokevirtual append : (Ljava/lang/String;)Ljava/lang/StringBuilder;
    //   565: swap
    //   566: invokevirtual append : (C)Ljava/lang/StringBuilder;
    //   569: pop
    //   570: goto -> 324
    //   573: new io/undertow/util/BadRequestException
    //   576: dup
    //   577: invokespecial <init> : ()V
    //   580: athrow
    //   581: getstatic io/undertow/client/http/HttpResponseParser$$generated.HTTP_STRING_3 : Lio/undertow/util/HttpString;
    //   584: aload_3
    //   585: swap
    //   586: invokevirtual setProtocol : (Lio/undertow/util/HttpString;)V
    //   589: aload_2
    //   590: swap
    //   591: putfield leftOver : B
    //   594: aload_2
    //   595: iconst_1
    //   596: putfield state : I
    //   599: goto -> 136
    //   602: pop
    //   603: iconst_2
    //   604: istore #4
    //   606: goto -> 609
    //   609: aload_1
    //   610: invokevirtual hasRemaining : ()Z
    //   613: ifeq -> 110
    //   616: aload_1
    //   617: invokevirtual get : ()B
    //   620: dup
    //   621: bipush #84
    //   623: if_icmpeq -> 691
    //   626: dup
    //   627: bipush #32
    //   629: if_icmpeq -> 670
    //   632: dup
    //   633: bipush #13
    //   635: if_icmpeq -> 662
    //   638: dup
    //   639: bipush #10
    //   641: if_icmpeq -> 662
    //   644: iconst_m1
    //   645: istore #4
    //   647: aload #7
    //   649: ldc 'HT'
    //   651: invokevirtual append : (Ljava/lang/String;)Ljava/lang/StringBuilder;
    //   654: swap
    //   655: invokevirtual append : (C)Ljava/lang/StringBuilder;
    //   658: pop
    //   659: goto -> 324
    //   662: new io/undertow/util/BadRequestException
    //   665: dup
    //   666: invokespecial <init> : ()V
    //   669: athrow
    //   670: getstatic io/undertow/client/http/HttpResponseParser$$generated.HTTP_STRING_4 : Lio/undertow/util/HttpString;
    //   673: aload_3
    //   674: swap
    //   675: invokevirtual setProtocol : (Lio/undertow/util/HttpString;)V
    //   678: aload_2
    //   679: swap
    //   680: putfield leftOver : B
    //   683: aload_2
    //   684: iconst_1
    //   685: putfield state : I
    //   688: goto -> 136
    //   691: pop
    //   692: iconst_3
    //   693: istore #4
    //   695: goto -> 698
    //   698: aload_1
    //   699: invokevirtual hasRemaining : ()Z
    //   702: ifeq -> 110
    //   705: aload_1
    //   706: invokevirtual get : ()B
    //   709: dup
    //   710: bipush #80
    //   712: if_icmpeq -> 780
    //   715: dup
    //   716: bipush #32
    //   718: if_icmpeq -> 759
    //   721: dup
    //   722: bipush #13
    //   724: if_icmpeq -> 751
    //   727: dup
    //   728: bipush #10
    //   730: if_icmpeq -> 751
    //   733: iconst_m1
    //   734: istore #4
    //   736: aload #7
    //   738: ldc 'HTT'
    //   740: invokevirtual append : (Ljava/lang/String;)Ljava/lang/StringBuilder;
    //   743: swap
    //   744: invokevirtual append : (C)Ljava/lang/StringBuilder;
    //   747: pop
    //   748: goto -> 324
    //   751: new io/undertow/util/BadRequestException
    //   754: dup
    //   755: invokespecial <init> : ()V
    //   758: athrow
    //   759: getstatic io/undertow/client/http/HttpResponseParser$$generated.HTTP_STRING_5 : Lio/undertow/util/HttpString;
    //   762: aload_3
    //   763: swap
    //   764: invokevirtual setProtocol : (Lio/undertow/util/HttpString;)V
    //   767: aload_2
    //   768: swap
    //   769: putfield leftOver : B
    //   772: aload_2
    //   773: iconst_1
    //   774: putfield state : I
    //   777: goto -> 136
    //   780: pop
    //   781: iconst_4
    //   782: istore #4
    //   784: goto -> 787
    //   787: aload_1
    //   788: invokevirtual hasRemaining : ()Z
    //   791: ifeq -> 110
    //   794: aload_1
    //   795: invokevirtual get : ()B
    //   798: dup
    //   799: bipush #47
    //   801: if_icmpeq -> 869
    //   804: dup
    //   805: bipush #32
    //   807: if_icmpeq -> 848
    //   810: dup
    //   811: bipush #13
    //   813: if_icmpeq -> 840
    //   816: dup
    //   817: bipush #10
    //   819: if_icmpeq -> 840
    //   822: iconst_m1
    //   823: istore #4
    //   825: aload #7
    //   827: ldc 'HTTP'
    //   829: invokevirtual append : (Ljava/lang/String;)Ljava/lang/StringBuilder;
    //   832: swap
    //   833: invokevirtual append : (C)Ljava/lang/StringBuilder;
    //   836: pop
    //   837: goto -> 324
    //   840: new io/undertow/util/BadRequestException
    //   843: dup
    //   844: invokespecial <init> : ()V
    //   847: athrow
    //   848: getstatic io/undertow/client/http/HttpResponseParser$$generated.HTTP_STRING_6 : Lio/undertow/util/HttpString;
    //   851: aload_3
    //   852: swap
    //   853: invokevirtual setProtocol : (Lio/undertow/util/HttpString;)V
    //   856: aload_2
    //   857: swap
    //   858: putfield leftOver : B
    //   861: aload_2
    //   862: iconst_1
    //   863: putfield state : I
    //   866: goto -> 136
    //   869: pop
    //   870: iconst_5
    //   871: istore #4
    //   873: goto -> 876
    //   876: aload_1
    //   877: invokevirtual hasRemaining : ()Z
    //   880: ifeq -> 110
    //   883: aload_1
    //   884: invokevirtual get : ()B
    //   887: dup
    //   888: bipush #48
    //   890: if_icmpeq -> 972
    //   893: dup
    //   894: bipush #49
    //   896: if_icmpeq -> 964
    //   899: dup
    //   900: bipush #32
    //   902: if_icmpeq -> 943
    //   905: dup
    //   906: bipush #13
    //   908: if_icmpeq -> 935
    //   911: dup
    //   912: bipush #10
    //   914: if_icmpeq -> 935
    //   917: iconst_m1
    //   918: istore #4
    //   920: aload #7
    //   922: ldc 'HTTP/'
    //   924: invokevirtual append : (Ljava/lang/String;)Ljava/lang/StringBuilder;
    //   927: swap
    //   928: invokevirtual append : (C)Ljava/lang/StringBuilder;
    //   931: pop
    //   932: goto -> 324
    //   935: new io/undertow/util/BadRequestException
    //   938: dup
    //   939: invokespecial <init> : ()V
    //   942: athrow
    //   943: getstatic io/undertow/client/http/HttpResponseParser$$generated.HTTP_STRING_7 : Lio/undertow/util/HttpString;
    //   946: aload_3
    //   947: swap
    //   948: invokevirtual setProtocol : (Lio/undertow/util/HttpString;)V
    //   951: aload_2
    //   952: swap
    //   953: putfield leftOver : B
    //   956: aload_2
    //   957: iconst_1
    //   958: putfield state : I
    //   961: goto -> 136
    //   964: pop
    //   965: bipush #6
    //   967: istore #4
    //   969: goto -> 994
    //   972: pop
    //   973: bipush #-2
    //   975: istore #4
    //   977: getstatic io/undertow/client/http/HttpResponseParser$$generated.HTTP_STRING_9 : Lio/undertow/util/HttpString;
    //   980: astore #6
    //   982: getstatic io/undertow/client/http/HttpResponseParser$$generated.STATE_BYTES_8 : [B
    //   985: astore #8
    //   987: bipush #6
    //   989: istore #5
    //   991: goto -> 164
    //   994: aload_1
    //   995: invokevirtual hasRemaining : ()Z
    //   998: ifeq -> 110
    //   1001: aload_1
    //   1002: invokevirtual get : ()B
    //   1005: dup
    //   1006: bipush #46
    //   1008: if_icmpeq -> 1076
    //   1011: dup
    //   1012: bipush #32
    //   1014: if_icmpeq -> 1055
    //   1017: dup
    //   1018: bipush #13
    //   1020: if_icmpeq -> 1047
    //   1023: dup
    //   1024: bipush #10
    //   1026: if_icmpeq -> 1047
    //   1029: iconst_m1
    //   1030: istore #4
    //   1032: aload #7
    //   1034: ldc 'HTTP/1'
    //   1036: invokevirtual append : (Ljava/lang/String;)Ljava/lang/StringBuilder;
    //   1039: swap
    //   1040: invokevirtual append : (C)Ljava/lang/StringBuilder;
    //   1043: pop
    //   1044: goto -> 324
    //   1047: new io/undertow/util/BadRequestException
    //   1050: dup
    //   1051: invokespecial <init> : ()V
    //   1054: athrow
    //   1055: getstatic io/undertow/client/http/HttpResponseParser$$generated.HTTP_STRING_14 : Lio/undertow/util/HttpString;
    //   1058: aload_3
    //   1059: swap
    //   1060: invokevirtual setProtocol : (Lio/undertow/util/HttpString;)V
    //   1063: aload_2
    //   1064: swap
    //   1065: putfield leftOver : B
    //   1068: aload_2
    //   1069: iconst_1
    //   1070: putfield state : I
    //   1073: goto -> 136
    //   1076: pop
    //   1077: bipush #7
    //   1079: istore #4
    //   1081: goto -> 1084
    //   1084: aload_1
    //   1085: invokevirtual hasRemaining : ()Z
    //   1088: ifeq -> 110
    //   1091: aload_1
    //   1092: invokevirtual get : ()B
    //   1095: dup
    //   1096: bipush #48
    //   1098: if_icmpeq -> 1172
    //   1101: dup
    //   1102: bipush #49
    //   1104: if_icmpeq -> 1194
    //   1107: dup
    //   1108: bipush #32
    //   1110: if_icmpeq -> 1151
    //   1113: dup
    //   1114: bipush #13
    //   1116: if_icmpeq -> 1143
    //   1119: dup
    //   1120: bipush #10
    //   1122: if_icmpeq -> 1143
    //   1125: iconst_m1
    //   1126: istore #4
    //   1128: aload #7
    //   1130: ldc 'HTTP/1.'
    //   1132: invokevirtual append : (Ljava/lang/String;)Ljava/lang/StringBuilder;
    //   1135: swap
    //   1136: invokevirtual append : (C)Ljava/lang/StringBuilder;
    //   1139: pop
    //   1140: goto -> 324
    //   1143: new io/undertow/util/BadRequestException
    //   1146: dup
    //   1147: invokespecial <init> : ()V
    //   1150: athrow
    //   1151: getstatic io/undertow/client/http/HttpResponseParser$$generated.HTTP_STRING_15 : Lio/undertow/util/HttpString;
    //   1154: aload_3
    //   1155: swap
    //   1156: invokevirtual setProtocol : (Lio/undertow/util/HttpString;)V
    //   1159: aload_2
    //   1160: swap
    //   1161: putfield leftOver : B
    //   1164: aload_2
    //   1165: iconst_1
    //   1166: putfield state : I
    //   1169: goto -> 136
    //   1172: pop
    //   1173: bipush #-2
    //   1175: istore #4
    //   1177: getstatic io/undertow/client/http/HttpResponseParser$$generated.HTTP_STRING_17 : Lio/undertow/util/HttpString;
    //   1180: astore #6
    //   1182: getstatic io/undertow/client/http/HttpResponseParser$$generated.STATE_BYTES_16 : [B
    //   1185: astore #8
    //   1187: bipush #8
    //   1189: istore #5
    //   1191: goto -> 164
    //   1194: pop
    //   1195: bipush #-2
    //   1197: istore #4
    //   1199: getstatic io/undertow/client/http/HttpResponseParser$$generated.HTTP_STRING_19 : Lio/undertow/util/HttpString;
    //   1202: astore #6
    //   1204: getstatic io/undertow/client/http/HttpResponseParser$$generated.STATE_BYTES_18 : [B
    //   1207: astore #8
    //   1209: bipush #8
    //   1211: istore #5
    //   1213: goto -> 164
  }
  
  static {
    Map<String, HttpString> map = HttpResponseParser.httpStrings();
    if (map.get("H") != null) {
      HTTP_STRING_3 = map.get("H");
    } else {
      map.get("H");
      HTTP_STRING_3 = new HttpString("H");
    } 
    if (map.get("HT") != null) {
      HTTP_STRING_4 = map.get("HT");
    } else {
      map.get("HT");
      HTTP_STRING_4 = new HttpString("HT");
    } 
    if (map.get("HTT") != null) {
      HTTP_STRING_5 = map.get("HTT");
    } else {
      map.get("HTT");
      HTTP_STRING_5 = new HttpString("HTT");
    } 
    if (map.get("HTTP") != null) {
      HTTP_STRING_6 = map.get("HTTP");
    } else {
      map.get("HTTP");
      HTTP_STRING_6 = new HttpString("HTTP");
    } 
    if (map.get("HTTP/") != null) {
      HTTP_STRING_7 = map.get("HTTP/");
    } else {
      map.get("HTTP/");
      HTTP_STRING_7 = new HttpString("HTTP/");
    } 
  }
}


/* Location:              G:\git\codeReviewLog\nginxWebUi\nginxWebUI-3.4.6.jar!\i\\undertow\client\http\HttpResponseParser$$generated.class
 * Java compiler version: 6 (50.0)
 * JD-Core Version:       1.1.3
 */